Workbook
Name Canopy: '[1]Rough Carpentry'!#REF!
Name Decks: '[1]Rough Carpentry'!#REF!
Name GROSS: [2]Preliminary!$F$17
Name GSF: '[1]Length & Area'!$B$20
Name Location: '[1]Project Information'!$B$5
Name Project: '[1]Project Information'!$B$4
Name Subtotal: '[3]STEP 1 - PROJECT DATA'!$B$7
Name Subtotal: 'STEP 1 - PROJECT DATA'!$B$7
Name Surcharge_Warranty: '[3]STEP 1 - PROJECT DATA'!$B$14
Name Surcharge_Warranty: 'STEP 1 - PROJECT DATA'!$B$14
Name ToiletAccessories: '[1]Interior Takeoff'!#REF!
Name Units: '[1]Unit Counts'!$J$35
Name Units2: [2]Preliminary!$I$20
Name WORK_ITEM: #REF!

Sheet TODO
A1: instructions - include locking and unlocking
A2: logo, branding and colors
A3: Put on FP Hub and get rid of everything else - FP Hub and Shared Drive
A11: STEP 1 - PROJECT DATA
A18: STEP 2 - GCs
A23: STEP 3 - SITE OPS
A29: STEP 4 - ESTIMATE

Sheet US_Holidays__2025_2034_
B1: Year | C1: Holiday | D1: Date
A2: 0 | B2: 2025 | C2: New Year's Day | D2: 45658
A3: 1 | B3: 2025 | C3: Memorial Day | D3: 45803
A4: 2 | B4: 2025 | C4: Independence Day | D4: 45842
A5: 3 | B5: 2025 | C5: Labor Day | D5: 45901
A6: 4 | B6: 2025 | C6: Thanksgiving | D6: 45988
A7: 5 | B7: 2025 | C7: Day After Thanksgiving | D7: 45989
A8: 6 | B8: 2025 | C8: Christmas | D8: 46016
A9: 7 | B9: 2026 | C9: New Year's Day | D9: 46023
A10: 8 | B10: 2026 | C10: Memorial Day | D10: 46167
A11: 9 | B11: 2026 | C11: Independence Day | D11: 46209
A12: 10 | B12: 2026 | C12: Labor Day | D12: 46272
A13: 11 | B13: 2026 | C13: Thanksgiving | D13: 46352
... A71: 69 | B71: 2034 | C71: Christmas | D71: 49303

Sheet COVER
C2: ='STEP 1 - PROJECT DATA'!D6& "." & 'STEP 1 - PROJECT DATA'!D7 -> E26-123.0 | I2: ='STEP 4 - ESTIMATE'!I2 -> Bid Due Date | J2: ='STEP 4 - ESTIMATE'!K2 -> 46010
C3: ='STEP 1 - PROJECT DATA'!C5 -> Project Name | D3: ='STEP 1 - PROJECT DATA'!D5 -> Name | H3: ='STEP 1 - PROJECT DATA'!C10 -> Expected Start | J3: ='STEP 4 - ESTIMATE'!K3 -> 46174
C4: Location | D4: ='STEP 1 - PROJECT DATA'!D8 -> 1234 Main St | H4: ='STEP 1 - PROJECT DATA'!C11 -> Expected Finish | J4: ='STEP 4 - ESTIMATE'!K4 -> 46235
D5: ='STEP 1 - PROJECT DATA'!D9 -> Minneapolis, MN | H5: Duration | J5: ='STEP 1 - PROJECT DATA'!D28 -> 2
C6: ='STEP 1 - PROJECT DATA'!C13 -> Architect | D6: ='STEP 1 - PROJECT DATA'!D13 -> TBD
C7: ='STEP 1 - PROJECT DATA'!C14 -> Plan Set | D7: ='STEP 1 - PROJECT DATA'!D14 -> TBD
C29: ='STEP 1 - PROJECT DATA'!D5 -> Name
C31: ='STEP 1 - PROJECT DATA'!D8 -> 1234 Main St
C33: ='STEP 1 - PROJECT DATA'!D9 -> Minneapolis, MN
C40: ='STEP 1 - PROJECT DATA'!G5 -> 0
C42: ='STEP 1 - PROJECT DATA'!G6 -> 0
E71: Estimator Information
E73: ='STEP 1 - PROJECT DATA'!C18 -> Prepared by | G73: ='STEP 1 - PROJECT DATA'!D18 -> 0
E74: ='STEP 1 - PROJECT DATA'!C19 -> Phone Number | G74: ='STEP 1 - PROJECT DATA'!D19
E75: ='STEP 1 - PROJECT DATA'!C20 -> Email Address | G75: ='STEP 1 - PROJECT DATA'!D20
E76: ='STEP 1 - PROJECT DATA'!C21 -> FP Office | G76: ='STEP 1 - PROJECT DATA'!D21 -> 10050 Crosstown Cir
E77: ='STEP 1 - PROJECT DATA'!C22 -> City, State, Zip | G77: ='STEP 1 - PROJECT DATA'!D22 -> Eden Prairie, MN 55344

Sheet STEP 1 - PROJECT DATA
J3: Estimator Information | K3: Phone Number | L3: Email Address
C4: Project Information | F4: Client Information | J4: Ben Urness | K4: 651 421-1392 | L4: burness@fpcinc.com
C5: Project Name | D5: Name | F5: Client | J5: Cal Pesola | K5: 612 751-4518 | L5: cpesola@fpcinc.com
C6: Estimate # | D6: E26-123 | F6: Contact Person | J6: Calvin Hayes | K6: 612 202-1934 | L6: chayes@fpcinc.com
C7: Revision # | D7: 0 | F7: Phone Number | J7: David Cook | K7: 612 718-9092 | L7: dcook@fpcinc.com
C8: Address | D8: 1234 Main St | F8: Email Address | J8: Haley Kasper | K8: 715 292-4851 | L8: hkasper@fpcinc.com
C9: City, State, Zip | D9: Minneapolis, MN | F9: Bid Due Date | G9: 46010 | J9: Isaac Freitag | K9: 612 545-7352 | L9: ifreitag@fpcinc.com
C10: Expected Start | D10: 46174 | J10: Jared Houle | K10: 651 324-7041 | L10: jhoule@fpcinc.com
C11: Expected Finish | D11: 46235 | J11: Justin Gunderson | K11: 612 366-9181 | L11: jgunderson@fpcinc.com
C12: Project Size | D12: 10 | J12: Kevin Swanson | K12: 612 817-6835 | L12: kswanson@fpcinc.com
C13: Architect | D13: TBD | J13: Spencer Will | K13: 952 818-4711 | L13: swill@fpcinc.com
C14: Plan Set | D14: TBD
J15: Target Profit Percentages
C17: Estimator Information | F17: Contingency, Fee, Insurances | J17: Project Size (Low) | K17: Project Size (High) | L17: Profit %
C18: Prepared by | F18: Construction Contingency | G18: 0 | J18: 0 | K18: 10000 | L18: 0.17
C19: Phone Number | D19: =_xlfn.XLOOKUP(D18,$J$4:$J$12,$K$4:$K$12,"") | F19: Design Contingency | G19: 0 | J19: 10000 | K19: 100000 | L19: 0.12
C20: Email Address | D20: =_xlfn.XLOOKUP(D18,$J$4:$J$12,$L$4:$L$12,"") | F20: Builders Risk Insurance | G20: 0 | J20: 100000 | K20: 250000 | L20: 0.09
C21: FP Office | D21: 10050 Crosstown Cir | F21: Special Insurance | G21: 0 | J21: 250000 | K21: 500000 | L21: 0.08
C22: City, State, Zip | D22: Eden Prairie, MN 55344 | F22: General Liability Insurance | G22: 0.01 | J22: 500000 | K22: 2000000 | L22: 0.07
F23: Bond | G23: 0 | J23: 2000000 | K23: 3000000 | L23: 0.06
F24: Fee | G24: 0.05 | J24: 3000000 | K24: 5000000 | L24: 0.05
J25: 5000000 | K25: 8000000 | L25: 0.04
C27: Project Duration | F27: Project Type and Sector | J27: Project Type | K27: Description
C28: Months | D28: =YEARFRAC(D10, D11) * 12 -> 2 | F28: Project Type | J28: Adaptive Reuse | K28: Repurposing existing buildings for new uses.
C29: Weeks | D29: =(D11 - D10) / 7 -> 8.7142857 | F29: Market Sector | J29: Ground-Up (New Construction) | K29: New builds from scratch.
C30: Total Calendar Days | D30: =D11-D10 -> 61 | J30: Renovation / Remodel | K30: Updates or overhauls to existing structures.
C31: Working Days | D31: =NETWORKDAYS(D10, D11, US_Holidays__2025_2034_!D2:D71) -> 44 | J31: Office Tenant Improvement (TI) | K31: Interior buildouts for new or existing office tenants.
J32: Site Development | K32: Prepping land for future construction.
C34: Building Permit Calculation | J34: Market Sector | K34: Description
J35: Commercial | K35: Retail, Grocery Store, Auto, Banks
C36: $1.00 - $500.00 | D36: =IF('STEP 2 - GCs'!H35 <501, 'STEP 2 - GCs'!H35, 0) -> 0 | E36: =IF(D36>0,36.7,0) -> 0 | J36: Restaurant | K36: Quick Service Restaurant (QSR), Fast Casual, Casual Dining, Fine Dining, Food Hall, Coffee Shop
C37: $501.00 - $2,000.00 | D37: =IF(AND(501 <'STEP 2 - GCs'!H35,'STEP 2 - GCs'!H35 < 2001), 'STEP 2 - GCs'!H35, 0) -> 0 | E37: =IF(D37>0,SUM((D37-500)*0.045)+36.7,0) -> 0 | J37: Healthcare | K37: Medical Clinics, Dental Offices, Animal Health/Vet Clinics
C38: $2,001.00 - $25,000.00 | D38: =IF(AND(2001 <'STEP 2 - GCs'!H35,'STEP 2 - GCs'!H35 < 25001), 'STEP 2 - GCs'!H35, 0) -> 0 | E38: =IF(D38>0,SUM((D38-2000)*0.0206)+104.2,0) -> 0 | J38: Housing and Hotel | K38: Multi-family, Senior Living, Single Family Homes, Hotels
C39: $25,001.00 - $50,000.00 | D39: =IF(AND(25001 <'STEP 2 - GCs'!H35,'STEP 2 - GCs'!H35 < 50001), 'STEP 2 - GCs'!H35, 0) -> 0 | E39: =IF(D39>0,SUM((D39-25000)*0.0149)+578,0) -> 0 | J39: Industrial | K39: Manufacturing, Warehouses, Cold Storage, Self-Storage
C40: $50,001.00 - $100,000.00 | D40: =IF(AND(50001 <'STEP 2 - GCs'!H35,'STEP 2 - GCs'!H35 < 100001), 'STEP 2 - GCs'!H35, 0) -> 0 | E40: =IF(D40>0,SUM((D40-50000)*0.0106)+950.5,0) -> 0 | J40: Government | K40: City Buildings, Courthouses, Post Offices
C41: $100,001.00 - $500,000.00 | D41: =IF(AND(100001 <'STEP 2 - GCs'!H35,'STEP 2 - GCs'!H35 < 500001), 'STEP 2 - GCs'!H35, 0) -> 117389 | E41: =IF(D41>0,SUM(((D41-100000)*0.0084)+1480.5),0) -> 1626.5676 | J41: Educational | K41: Schools, Colleges, Universities, Daycare
C42: $500,001.00 - $1,000,000.00 | D42: =IF(AND(500001 <'STEP 2 - GCs'!H35,'STEP 2 - GCs'!H35 < 1000001), 'STEP 2 - GCs'!H35, 0) -> 0 | E42: =IF(D42>0,SUM((D42-500000)*0.0069)+4840.5,0) -> 0 | J42: Workplace | K42: Office Buildings (Traditional, Open, Hybrid, Coworking)
C43: $1,000,001.00 and Up | D43: =IF('STEP 2 - GCs'!H35 > 1000001, 'STEP 2 - GCs'!H35, 0) -> 0 | E43: =IF(D43>0,SUM((D43-1000000)*0.0056)+8290.5,0) -> 0
C44: Building Permit Fee | F44: =SUM(E36:E43) -> 1626.5676
C45: Plan Review Fee | F45: =SUM(F44)*0.65 -> 1057.2689
C46: MN State Surcharge | F46: =SUM(D36:D43)*0.0005 -> 58.6945
C48: Total Building Permit Cost | F48: =SUM(F44:F46) -> 2742.531
C54: For Multi-Family / Ground-Ups
C56: Project Information | I56: Enter into Estimate
C57: Gross SF | D57: =D12 -> 10 | I57: 03-0000 | J57: Concrete Strip Footing | K57: =E63+E64 -> 2050 | L57: lf
C58: # of Units | D58: 100 | I58: 03-0000 | J58: Concrete Fnd Pads | K58: =E65/(50*50)*4 -> 96 | L58: ea
I59: 03-0000 | J59: Concrete Walls | K59: =E63*E69 -> 18000 | L59: sf
C60: Building Parameters | I60: 03-0000 | J60: SOG | K60: =E65 -> 60000 | L60: sf
C61: Building Parameters | E61: Quantity | F61: Unit
C62: # of Buildings | E62: 1 | F62: ea | I62: 03-4100 | J62: Precast Structural Concrete | K62: =E66 -> 120000 | L62: sf
C63: Building Perimeter | E63: 1500 | F63: lf
C64: Building Length (measured down center) | E64: 550 | F64: lf | I64: 03-5413 | J64: Gypsum Cement Underlayment | K64: =E67 -> 300000 | L64: sf
C65: Building Footprint | E65: 60000 | F65: sf
C66: Podium Area (all levels) | E66: 120000 | F66: sf | I66: 04-0000 | J66: Masonry - Veneer | K66: =E79+E80 -> 34650 | L66: sf
C67: Woodframed Area (including podium level) | E67: 300000 | F67: sf
C68: Amenity Deck | E68: 25000 | F68: sf | I68: 06-1000 | J68: Loose Lumber and Roof Joists | K68: =E67 -> 300000 | L68: sf
C69: Foundation Height Below Grade | E69: 12 | F69: ft
C70: Podium Height Above Grade | E70: 20 | F70: ft | I70: 07-1000 | J70: Waterproofing | K70: =E63*E69 -> 18000 | L70: sf
C71: Podium to Parapet Height | E71: 50 | F71: ft
C72: Levels Above Podium | E72: 5 | F72: ea | I72: 07-1413 | J72: Hot-Fluid-Applied Waterproofing | K72: =E68 -> 25000 | L72: sf
C74: Exterior Skin | I74: 07-2500 | J74: Weather Barriers | K74: =E75 -> 115500 | L74: sf
C75: Total | E75: =E63*(E70+E71)*1.1 -> 115500 | F75: sf
C76: Material | D76: Percentage | E76: Area | F76: Unit | I76: 07-2400 | J76: Stucco, Plaster, EIFS | K76: =E84 -> 0 | L76: sf
C77: Precast | D77: 0 | E77: =D77*$E$75 -> 0 | F77: sf
C78: Rock Face Block | D78: 0 | E78: =D78*$E$75 -> 0 | F78: sf | I78: 07-3113 | J78: Asphalt Shingles | K78: =E67/E72 -> 60000 | L78: sf
C79: Brick | D79: 0.3 | E79: =D79*$E$75 -> 34650 | F79: sf | I79: 07-3113 | J79: Gutters and Downspouts | K79: =E63 -> 1500 | L79: lf
C80: Stone | D80: 0 | E80: =D80*$E$75 -> 0 | F80: sf
C81: Metal Panel | D81: 0 | E81: =D81*$E$75 -> 0 | F81: sf | I81: 07-4213 | J81: Metal Panel Siding | K81: =E81+E82 -> 0 | L81: sf
C82: ACM Panel | D82: 0 | E82: =D82*$E$75 -> 0 | F82: sf | I82: 07-4600 | J82: Siding | K82: =E83 -> 55440 | L82: sf
C83: Fiber Cement | D83: 0.48 | E83: =D83*$E$75 -> 55440 | F83: sf
C84: Stucco | D84: 0 | E84: =D84*$E$75 -> 0 | F84: sf | I84: 07-5000 | J84: Membrane Roofing | K84: =E67/E72 -> 60000 | L84: sf
C85: Windows/Patio Doors | D85: 0.2 | E85: =D85*$E$75 -> 23100 | F85: sf | G85: 0.2
C86: Alum Storefront | D86: 0.02 | E86: =D86*$E$75 -> 2310 | F86: sf | G86: 0.02 | I86: 08-5413 | J86: Windows and Patio Doors | K86: =E85 -> 23100 | L86: sf
C87: Total | D87: =SUM(D77:D86) -> 1 | E87: =SUM(E77:E86) -> 115500 | F87: sf | I87: 08-4000 | J87: Aluminum Entrances & Storefronts | K87: =E86 -> 2310 | L87: sf

Sheet STEP 2 - GCs
M1: Low Risk
C2: ='STEP 1 - PROJECT DATA'!D6& "." & 'STEP 1 - PROJECT DATA'!D7 -> E26-123.0 | I2: ='STEP 4 - ESTIMATE'!I2 -> Bid Due Date | J2: ='STEP 4 - ESTIMATE'!K2 -> 46010 | M2: Medium Risk
C3: ='STEP 1 - PROJECT DATA'!C5 -> Project Name | D3: ='STEP 1 - PROJECT DATA'!D5 -> Name | E3: Supervision & General Conditions | H3: ='STEP 1 - PROJECT DATA'!C10 -> Expected Start | J3: ='STEP 4 - ESTIMATE'!K3 -> 46174 | M3: High Risk
C4: Location | D4: ='STEP 1 - PROJECT DATA'!D8 -> 1234 Main St | H4: ='STEP 1 - PROJECT DATA'!C11 -> Expected Finish | J4: ='STEP 4 - ESTIMATE'!K4 -> 46235
D5: ='STEP 1 - PROJECT DATA'!D9 -> Minneapolis, MN | H5: Duration | J5: ='STEP 1 - PROJECT DATA'!D28 -> 2
C6: ='STEP 1 - PROJECT DATA'!C13 -> Architect | D6: ='STEP 1 - PROJECT DATA'!D13 -> TBD
C7: ='STEP 1 - PROJECT DATA'!C14 -> Plan Set | D7: ='STEP 1 - PROJECT DATA'!D14 -> TBD | J7: Bldg. Sqft.
J8: ='STEP 1 - PROJECT DATA'!D12 -> 10
C9: Code | D9: Description | E9: Utilization | F9: Quantity | G9: Unit | H9: Rate | I9: Total | J9: Cost/S.F.
C10: DIVISION 01 — SUPERVISION | D10: GENERAL CONDITIONS
C12: 01-0410 | D12: Sr Superintendent | E12: 1 | F12: =$J$5*4.33*E12*40 -> 346.4 | G12: hr | H12: 125 | I12: =F12*H12 -> 43300 | J12: =IF($J$8=0, 0, I12/$J$8) -> 4330
C13: 01-0420 | D13: Superintendent | E13: 0 | F13: =$J$5*4.33*E13*40 -> 0 | G13: hr | H13: 110 | I13: =F13*H13 -> 0 | J13: =IF($J$8=0, 0, I13/$J$8) -> 0
C14: 01-0430 | D14: Asst. Superintendent | E14: 0 | F14: =$J$5*4.33*E14*40 -> 0 | G14: hr | H14: 85 | I14: =F14*H14 -> 0 | J14: =IF($J$8=0, 0, I14/$J$8) -> 0
H16: Total Supervision | I16: =SUM(I11:I15) -> 43300 | J16: =IF($J$8=0, 0, I16/$J$8) -> 4330
C17: DIVISION 01 — DESIGN | D17: GENERAL CONDITIONS | E17: =SUM(I18:I24) -> 0
C19: 01-0001 | D19: Preconstruction Fees | F19: 0 | G19: ls | H19: 0 | I19: =F19*H19 -> 0 | J19: =IF($J$8=0, 0, I19/$J$8) -> 0
C20: 01-0130 | D20: Design - Architecture | F20: 0 | G20: ls | H20: 0 | I20: =F20*H20 -> 0 | J20: =IF($J$8=0, 0, I20/$J$8) -> 0
C21: 01-0160 | D21: Design - Civil | F21: 0 | G21: ls | H21: 0 | I21: =F21*H21 -> 0 | J21: =IF($J$8=0, 0, I21/$J$8) -> 0
C22: 01-0180 | D22: Design - MEP | F22: 0 | G22: ls | H22: 0 | I22: =F22*H22 -> 0 | J22: =IF($J$8=0, 0, I22/$J$8) -> 0
C23: 01-0210 | D23: Design - Structural | F23: 0 | G23: ls | H23: 0 | I23: =F23*H23 -> 0 | J23: =IF($J$8=0, 0, I23/$J$8) -> 0
C25: DIVISION 01 — PROJECT MANAGEMENT | D25: GENERAL CONDITIONS | E25: =SUM(I26:I32) -> 23382 | L25: =E25/'STEP 4 - ESTIMATE'!$I$341 -> 0.19918473 | M25: Min 2%
C27: 01-0310 | D27: Project Executive | E27: 0 | F27: =$J$5*4.33*E27*40 -> 0 | G27: hr | H27: 175 | I27: =F27*H27 -> 0 | J27: =IF($J$8=0, 0, I27/$J$8) -> 0
C28: 01-0320 | D28: Sr Project Manager | E28: 0.5 | F28: =$J$5*4.33*E28*40 -> 173.2 | G28: hr | H28: 135 | I28: =F28*H28 -> 23382 | J28: =IF($J$8=0, 0, I28/$J$8) -> 2338.2
C29: 01-0330 | D29: Project Manager | E29: 0 | F29: =$J$5*4.33*E29*40 -> 0 | G29: hr | H29: 120 | I29: =F29*H29 -> 0 | J29: =IF($J$8=0, 0, I29/$J$8) -> 0
C30: 01-0340 | D30: Project Engineer | E30: 0 | F30: =$J$5*4.33*E30*40 -> 0 | G30: hr | H30: 85 | I30: =F30*H30 -> 0 | J30: =IF($J$8=0, 0, I30/$J$8) -> 0
C31: 01-0510 | D31: Project Assistant | E31: 0 | F31: =$J$5*4.33*E31*40 -> 0 | G31: hr | H31: 55 | I31: =F31*H31 -> 0 | J31: =IF($J$8=0, 0, I31/$J$8) -> 0
C33: DIVISION 01 — GENERAL CONDITIONS | D33: GENERAL CONDITIONS | E33: =SUM(I34:I57) -> 41316.85
C35: 01-0610 | D35: Safety Consultant | E35: REQUIRED | F35: 0.0002 | G35: % | H35: 117389 | I35: =F35*H35 -> 23.4778 | J35: =IF($J$8=0, 0, I35/$J$8) -> 2.34778 | L35: ='STEP 4 - ESTIMATE'!$I$341 -> 117388.51 | M35: Enter this amount in column H when estimate complete
C36: 01-1000 | D36: Small Tools | F36: =$J$5 -> 2 | G36: mo | H36: 500 | I36: =F36*H36 -> 1000 | J36: =IF($J$8=0, 0, I36/$J$8) -> 100
C37: 01-1200 | D37: Fuel and Vehicle Charges | E37: 1 | F37: =$J$5*E37 -> 2 | G37: mo | H37: 1200 | I37: =F37*H37 -> 2400 | J37: =IF($J$8=0, 0, I37/$J$8) -> 240
C38: 01-1400 | D38: Travel and Meals | F38: 0 | G38: mo | H38: 0 | I38: =F38*H38 -> 0 | J38: =IF($J$8=0, 0, I38/$J$8) -> 0
C39: 01-1600 | D39: Procore | E39: REQUIRED | F39: 0.0019 | G39: % | H39: =H35 -> 117389 | I39: =F39*H39 -> 223.0391 | J39: =IF($J$8=0, 0, I39/$J$8) -> 22.30391 | L39: Copies cell from H35
C40: 01-4010 | D40: Quality | F40: =$J$5 -> 2 | G40: mo | H40: 500 | I40: =F40*H40 -> 1000 | J40: =IF($J$8=0, 0, I40/$J$8) -> 100
C41: 01-5110 | D41: Temp Office Set up and Takedown | F41: 1 | G41: ea | H41: 9000 | I41: =F41*H41 -> 9000 | J41: =IF($J$8=0, 0, I41/$J$8) -> 900
C42: 01-5110 | D42: Temp Office | F42: =$J$5 -> 2 | G42: mo | H42: 850 | I42: =F42*H42 -> 1700 | J42: =IF($J$8=0, 0, I42/$J$8) -> 170
C43: 01-5111 | D43: Cell Phone | E43: REQUIRED | F43: =$J$5 -> 2 | G43: mo | H43: 135 | I43: =F43*H43 -> 270 | J43: =IF($J$8=0, 0, I43/$J$8) -> 27
C44: 01-5112 | D44: Jobsite Office Equipment | F44: =$J$5 -> 2 | G44: mo | H44: 250 | I44: =F44*H44 -> 500 | J44: =IF($J$8=0, 0, I44/$J$8) -> 50
C45: 01-5114 | D45: Project Computers / Internet | F45: =$J$5 -> 2 | G45: mo | H45: 300 | I45: =F45*H45 -> 600 | J45: =IF($J$8=0, 0, I45/$J$8) -> 60
C46: 01-5120 | D46: Storage Trailer | F46: =$J$5 -> 2 | G46: mo | H46: 800 | I46: =F46*H46 -> 1600 | J46: =IF($J$8=0, 0, I46/$J$8) -> 160
C47: 01-5130 | D47: Dumpsters | F47: =$J$5*4 -> 8 | G47: ea | H47: 650 | I47: =F47*H47 -> 5200 | J47: =IF($J$8=0, 0, I47/$J$8) -> 520
C48: 01-5140 | D48: Temporary Toilets | F48: =$J$5 -> 2 | G48: mo | H48: 1000 | I48: =F48*H48 -> 2000 | J48: =IF($J$8=0, 0, I48/$J$8) -> 200
C49: 01-5150 | D49: Temporary Fire Extinguishers | F49: =J8/3000 -> 0.0033333333 | G49: ea | H49: 100 | I49: =F49*H49 -> 0.33333333 | J49: =IF($J$8=0, 0, I49/$J$8) -> 0.033333333
C50: 01-5160 | D50: Temporary Project Signs | F50: 1 | G50: ea | H50: 1500 | I50: =F50*H50 -> 1500 | J50: =IF($J$8=0, 0, I50/$J$8) -> 150
C51: 01-5170 | D51: Temporary Electric | F51: =$J$5 -> 2 | G51: mo | H51: 2500 | I51: =F51*H51 -> 5000 | J51: =IF($J$8=0, 0, I51/$J$8) -> 500
C52: 01-5180 | D52: Temporary Gas (not winter heat) | F52: =$J$5 -> 2 | G52: mo | H52: 900 | I52: =F52*H52 -> 1800 | J52: =IF($J$8=0, 0, I52/$J$8) -> 180
C53: 01-5190 | D53: Temporary Water | F53: =$J$5 -> 2 | G53: mo | H53: 650 | I53: =F53*H53 -> 1300 | J53: =IF($J$8=0, 0, I53/$J$8) -> 130
C54: 01-6010 | D54: Courier services | F54: =$J$5 -> 2 | G54: mo | H54: 350 | I54: =F54*H54 -> 700 | J54: =IF($J$8=0, 0, I54/$J$8) -> 70
C55: 01-6020 | D55: Plan Reproduction | F55: =$J$5 -> 2 | G55: mo | H55: 250 | I55: =F55*H55 -> 500 | J55: =IF($J$8=0, 0, I55/$J$8) -> 50
C56: 01-7010 | D56: Legal Fees | F56: 1 | G56: ls | H56: 5000 | I56: =F56*H56 -> 5000 | J56: =IF($J$8=0, 0, I56/$J$8) -> 500
H58: Total Design, PM and GCs | I58: =SUM(I18:I57) -> 64698.85 | J58: =IF($J$8=0, 0, I58/$J$8) -> 6469.885
H61: GCs by % | I61: =(I16+I58)/'STEP 4 - ESTIMATE'!I331 -> 0.9752128

Sheet STEP 3 - SITE OPS
C2: ='STEP 2 - GCs'!C2 -> E26-123.0 | I2: ='STEP 4 - ESTIMATE'!I2 -> Bid Due Date | J2: ='STEP 4 - ESTIMATE'!K2 -> 46010 | M2: Low Risk
C3: ='STEP 2 - GCs'!C3 -> Project Name | D3: ='STEP 2 - GCs'!D3 -> Name | E3: Site Operations | H3: ='STEP 1 - PROJECT DATA'!C10 -> Expected Start | J3: ='STEP 4 - ESTIMATE'!K3 -> 46174 | M3: Medium Risk
C4: ='STEP 2 - GCs'!C4 -> Location | D4: ='STEP 2 - GCs'!D4 -> 1234 Main St | H4: ='STEP 1 - PROJECT DATA'!C11 -> Expected Finish | J4: ='STEP 4 - ESTIMATE'!K4 -> 46235 | M4: High Risk
D5: ='STEP 2 - GCs'!D5 -> Minneapolis, MN | H5: Duration | J5: ='STEP 1 - PROJECT DATA'!D28 -> 2
C6: ='STEP 2 - GCs'!C6 -> Architect | D6: ='STEP 2 - GCs'!D6 -> TBD
C7: ='STEP 2 - GCs'!C7 -> Plan Set | D7: ='STEP 2 - GCs'!D7 -> TBD | J7: Bldg. Sqft.
J8: ='STEP 4 - ESTIMATE'!K8 -> 10
C9: Code | D9: Description | F9: Quantity | G9: Unit | H9: Rate | I9: Total | J9: Cost/S.F.
C10: 02-0000 — SITE OPERATIONS | D10: GENERAL CONDITIONS | E10: =SUM(I11:I28) -> 2.5
C12: 02-3200 | D12: Soil Borings | F12: 0 | G12: ls | H12: 0 | I12: =F12*H12 -> 0 | J12: =IF($J$8=0, 0, I12/$J$8) -> 0
C13: 02-5100 | D13: FFE Relocation | F13: 0 | G13: ls | H13: 0 | I13: =F13*H13 -> 0 | J13: =IF($J$8=0, 0, I13/$J$8) -> 0
C14: 02-8213 | D14: Abatement | F14: 0 | G14: ls | H14: 0 | I14: =F14*H14 -> 0 | J14: =IF($J$8=0, 0, I14/$J$8) -> 0
C15: 02-9010 | D15: Progress Cleaning - Payroll | E15: 0 | F15: =$J$5*4.33*E15*40 -> 0 | G15: hr | H15: 74 | I15: =F15*H15 -> 0 | J15: =IF($J$8=0, 0, I15/$J$8) -> 0
C16: 02-9010 | D16: Progress Cleaning - Hired | E16: 0 | F16: =$J$5*4.33*E16*40 -> 0 | G16: hr | H16: 54 | I16: =F16*H16 -> 0 | J16: =IF($J$8=0, 0, I16/$J$8) -> 0
C17: 02-9015 | D17: Safety | F17: 0 | G17: mo | H17: 500 | I17: =F17*H17 -> 0 | J17: =IF($J$8=0, 0, I17/$J$8) -> 0
C18: 02-9020 | D18: Temp Protection | F18: =J8 -> 10 | G18: sf | H18: 0.25 | I18: =F18*H18 -> 2.5 | J18: =IF($J$8=0, 0, I18/$J$8) -> 0.25
C19: 02-9025 | D19: Temporary Partitions | F19: 0 | G19: ea | H19: 5000 | I19: =F19*H19 -> 0 | J19: =IF($J$8=0, 0, I19/$J$8) -> 0
C20: 02-9030 | D20: Traffic Control and Jersey Barriers | F20: 0 | G20: lf | H20: 25 | I20: =F20*H20 -> 0 | J20: =IF($J$8=0, 0, I20/$J$8) -> 0
C21: 02-9035 | D21: Temporary Fencing | F21: 0 | G21: lf | H21: 15 | I21: =F21*H21 -> 0 | J21: =IF($J$8=0, 0, I21/$J$8) -> 0
C22: 02-9040 | D22: Scrim | F22: 0 | G22: lf | H22: 20 | I22: =F22*H22 -> 0 | J22: =IF($J$8=0, 0, I22/$J$8) -> 0
C23: 02-9045 | D23: Temp Access Roads | F23: 0 | G23: ls | H23: 5000 | I23: =F23*H23 -> 0 | J23: =IF($J$8=0, 0, I23/$J$8) -> 0
C24: 02-9050 | D24: Site Security | F24: 0 | G24: mo | H24: 2000 | I24: =F24*H24 -> 0 | J24: =IF($J$8=0, 0, I24/$J$8) -> 0
C25: 02-9055 | D25: Site Security Cameras | F25: 0 | G25: mo | H25: 1000 | I25: =F25*H25 -> 0 | J25: =IF($J$8=0, 0, I25/$J$8) -> 0
C26: 02-9060 | D26: Jobsite Camera | F26: 0 | G26: mo | H26: 1000 | I26: =F26*H26 -> 0 | J26: =IF($J$8=0, 0, I26/$J$8) -> 0
C27: 02-9065 | D27: Construction Permits (not building permit) | F27: 0 | G27: ea | H27: 0 | I27: =F27*H27 -> 0 | J27: =IF($J$8=0, 0, I27/$J$8) -> 0
H29: Total Site Operations | I29: =SUM(I11:I28) -> 2.5 | J29: =IF($J$8=0, 0, I29/$J$8) -> 0.25
C30: 02-4100 — DEMOLITION | D30: GENERAL CONDITIONS | E30: =SUM(I31:I34) -> 0
C32: 02-4100 | D32: Demolition | F32: 0 | G32: sf | H32: 6 | I32: =F32*H32 -> 0 | J32: =IF($J$8=0, 0, I32/$J$8) -> 0
C33: 02-4100 | D33: Demolition - Sawcutting | F33: 0 | G33: ls | H33: 0 | I33: =F33*H33 -> 0 | J33: =IF($J$8=0, 0, I33/$J$8) -> 0
H35: Total Demolition | I35: =SUM(I31:I34) -> 0 | J35: =IF($J$8=0, 0, I35/$J$8) -> 0
C36: 02-9005 — FINAL CLEANING | D36: GENERAL CONDITIONS | E36: =SUM(I37:I39) -> 0
C38: 02-9005 | D38: Final Cleaning | F38: 0 | G38: ea | H38: 2500 | I38: =F38*H38 -> 0 | J38: =IF($J$8=0, 0, I38/$J$8) -> 0
H40: Total Final Cleaning | I40: =SUM(I37:I39) -> 0 | J40: =IF($J$8=0, 0, I40/$J$8) -> 0
C41: 02-9070 — SWPPP PERMIT | D41: GENERAL CONDITIONS | E41: =SUM(I42:I44) -> 0
C43: 02-9070 | D43: SWPPP Permit | F43: 0 | G43: ea | H43: 400 | I43: =F43*H43 -> 0 | J43: =IF($J$8=0, 0, I43/$J$8) -> 0
H45: Total SWPPP Permit | I45: =SUM(I42:I44) -> 0 | J45: =IF($J$8=0, 0, I45/$J$8) -> 0
C46: 02-9200 — SURVEY & LAYOUT | D46: GENERAL CONDITIONS | E46: =SUM(I47:I50) -> 0
C48: 02-9200 | D48: Survey & Layout | F48: 0 | G48: ls | H48: 0 | I48: =F48*H48 -> 0 | J48: =IF($J$8=0, 0, I48/$J$8) -> 0
C49: 02-9200 | D49: Survey & Layout - Floor Scanning | F49: 0 | G49: ls | H49: 0 | I49: =F49*H49 -> 0 | J49: =IF($J$8=0, 0, I49/$J$8) -> 0
H51: Total Survey and Layout | I51: =SUM(I47:I50) -> 0 | J51: =IF($J$8=0, 0, I51/$J$8) -> 0
C52: 02-9300 — BUILDING AND SITE SERVICES | D52: GENERAL CONDITIONS | E52: =SUM(I53:I61) -> 0
C54: 02-9305 | D54: City Requirements | F54: 0 | G54: ls | H54: 0 | I54: =F54*H54 -> 0 | J54: =IF($J$8=0, 0, I54/$J$8) -> 0
C55: 02-9307 | D55: Knox Box | F55: 0 | G55: ea | H55: 650 | I55: =F55*H55 -> 0 | J55: =IF($J$8=0, 0, I55/$J$8) -> 0
C56: 02-9310 | D56: Permanent Power Service | F56: 0 | G56: ls | H56: 0 | I56: =F56*H56 -> 0 | J56: =IF($J$8=0, 0, I56/$J$8) -> 0
C57: 02-9315 | D57: Temporary Power Service | F57: 0 | G57: ls | H57: 0 | I57: =F57*H57 -> 0 | J57: =IF($J$8=0, 0, I57/$J$8) -> 0
C58: 02-9320 | D58: Gas Service | F58: 0 | G58: ls | H58: 0 | I58: =F58*H58 -> 0 | J58: =IF($J$8=0, 0, I58/$J$8) -> 0
C59: 02-9325 | D59: Cable Service | F59: 0 | G59: ls | H59: 0 | I59: =F59*H59 -> 0 | J59: =IF($J$8=0, 0, I59/$J$8) -> 0
C60: 02-9330 | D60: Data Service | F60: 0 | G60: ls | H60: 0 | I60: =F60*H60 -> 0 | J60: =IF($J$8=0, 0, I60/$J$8) -> 0
H62: Total Building and Site Services | I62: =SUM(I53:I61) -> 0 | J62: =IF($J$8=0, 0, I62/$J$8) -> 0
C63: 02-9400 — SITE EQUIPMENT | D63: GENERAL CONDITIONS | E63: =SUM(I64:I71) -> 0
C65: 02-9405 | D65: Material Hoist / Trash Chute | F65: 0 | G65: mo | H65: 6500 | I65: =F65*H65 -> 0 | J65: =IF($J$8=0, 0, I65/$J$8) -> 0
C66: 02-9410 | D66: Scaffolding & Platforms | F66: 0 | G66: mo | H66: 0 | I66: =F66*H66 -> 0 | J66: =IF($J$8=0, 0, I66/$J$8) -> 0
C67: 02-9415 | D67: Crane Rental | F67: 0 | G67: mo | H67: 0 | I67: =F67*H67 -> 0 | J67: =IF($J$8=0, 0, I67/$J$8) -> 0
C68: 02-9420 | D68: Equipment Rental | F68: 0 | G68: mo | H68: 2000 | I68: =F68*H68 -> 0 | J68: =IF($J$8=0, 0, I68/$J$8) -> 0
C69: 02-9425 | D69: Forklift Rental | F69: 0 | G69: mo | H69: 4000 | I69: =F69*H69 -> 0 | J69: =IF($J$8=0, 0, I69/$J$8) -> 0
C70: 02-9430 | D70: Street Sweeping | F70: 0 | G70: mo | H70: 300 | I70: =F70*H70 -> 0 | J70: =IF($J$8=0, 0, I70/$J$8) -> 0
H72: Total Site Equipment | I72: =SUM(I64:I71) -> 0 | J72: =IF($J$8=0, 0, I72/$J$8) -> 0
C73: 02-9500 — SPECIAL INSPECTIONS | D73: GENERAL CONDITIONS | E73: =SUM(I74:I81) -> 0
C75: 02-9505 | D75: Construction Materials Testing | F75: 0 | G75: ls | H75: 0 | I75: =F75*H75 -> 0 | J75: =IF($J$8=0, 0, I75/$J$8) -> 0
C76: 02-9510 | D76: Vibration Monitoring | F76: 0 | G76: ls | H76: 0 | I76: =F76*H76 -> 0 | J76: =IF($J$8=0, 0, I76/$J$8) -> 0
C77: 02-9515 | D77: Acoustic Testing | F77: 0 | G77: ls | H77: 0 | I77: =F77*H77 -> 0 | J77: =IF($J$8=0, 0, I77/$J$8) -> 0
C78: 02-9520 | D78: Window Testing | F78: 0 | G78: ls | H78: 0 | I78: =F78*H78 -> 0 | J78: =IF($J$8=0, 0, I78/$J$8) -> 0
C79: 02-9525 | D79: Weather Barrier Testing | F79: 0 | G79: ls | H79: 0 | I79: =F79*H79 -> 0 | J79: =IF($J$8=0, 0, I79/$J$8) -> 0
C80: 02-9530 | D80: Gypcrete Testing | F80: 0 | G80: ls | H80: 0 | I80: =F80*H80 -> 0 | J80: =IF($J$8=0, 0, I80/$J$8) -> 0
H82: Total Site Special Inspections | I82: =SUM(I74:I81) -> 0 | J82: =IF($J$8=0, 0, I82/$J$8) -> 0

Sheet STEP 4 - ESTIMATE
C2: ='STEP 1 - PROJECT DATA'!D6& "." & 'STEP 1 - PROJECT DATA'!D7 -> E26-123.0 | I2: ='STEP 1 - PROJECT DATA'!F9 -> Bid Due Date | K2: ='STEP 1 - PROJECT DATA'!G9 -> 46010 | O2: Low Risk
C3: ='STEP 1 - PROJECT DATA'!C5 -> Project Name | D3: ='STEP 1 - PROJECT DATA'!D5 -> Name | E3: Detailed Estimate | H3: ='STEP 1 - PROJECT DATA'!C10 -> Expected Start | K3: ='STEP 1 - PROJECT DATA'!D10 -> 46174 | O3: Medium Risk
C4: Location | D4: ='STEP 1 - PROJECT DATA'!D8 -> 1234 Main St | H4: ='STEP 1 - PROJECT DATA'!C11 -> Expected Finish | K4: ='STEP 1 - PROJECT DATA'!D11 -> 46235 | O4: High Risk
D5: ='STEP 1 - PROJECT DATA'!D9 -> Minneapolis, MN | H5: Duration | K5: ='STEP 1 - PROJECT DATA'!D28 -> 2
C6: ='STEP 1 - PROJECT DATA'!C13 -> Architect | D6: ='STEP 1 - PROJECT DATA'!D13 -> TBD
C7: ='STEP 1 - PROJECT DATA'!C14 -> Plan Set | D7: ='STEP 1 - PROJECT DATA'!D14 -> TBD | J7: ='STEP 1 - PROJECT DATA'!C58 -> # of Units | K7: ='STEP 1 - PROJECT DATA'!C12 -> Project Size
J8: ='STEP 1 - PROJECT DATA'!D58 -> 100 | K8: ='STEP 1 - PROJECT DATA'!D12 -> 10
A9: TYPE | C9: Code | D9: Description | F9: Quantity | G9: Unit | H9: Unit Price | I9: Total | J9: Cost/Unit | K9: Cost/S.F. | O9: Vendor | P9: Actual
A10: TI | C10: DIVISION 01 — GENERAL CONDITIONS | D10: GENERAL CONDITIONS | E10: =SUM(I11:I14) -> 107998.85
A11: TI
A12: TI | C12: 01-0000.001 | D12: General Conditions | F12: 1 | G12: ls | H12: ='STEP 2 - GCs'!I58 -> 64698.85 | I12: =IF(ISNUMBER(F12), F12 * H12, 0) -> 64698.85 | J12: =IF($J$8=0, 0, I12/$J$8) -> 646.9885 | K12: =IF($K$8=0, 0, I12/$K$8) -> 6469.885 | O12: Fendler Patterson | P12: =I12 -> 64698.85 | S12: ='STEP 2 - GCs'!I58='STEP 4 - ESTIMATE'!I12 -> TRUE
A13: TI | C13: 01-0400.002 | D13: Supervision | F13: 1 | G13: ls | H13: ='STEP 2 - GCs'!I16 -> 43300 | I13: =IF(ISNUMBER(F13), F13 * H13, 0) -> 43300 | J13: =IF($J$8=0, 0, I13/$J$8) -> 433 | K13: =IF($K$8=0, 0, I13/$K$8) -> 4330 | O13: Fendler Patterson | P13: =I13 -> 43300 | S13: =I13='STEP 2 - GCs'!I16 -> TRUE
A14: TI
A15: TI | C15: DIVISION 02 — SITE OPERATIONS | D15: SITE OPERATIONS | E15: =SUM(I16:I25) -> 2.5
A16: TI
A17: TI | C17: 02-0000.001 | D17: Site Operations | F17: 1 | G17: ls | H17: ='STEP 3 - SITE OPS'!I29 -> 2.5 | I17: =IF(ISNUMBER(F17), F17 * H17, 0) -> 2.5 | J17: =IF($J$8=0, 0, I17/$J$8) -> 0.025 | K17: =IF($K$8=0, 0, I17/$K$8) -> 0.25 | S17: =I17='STEP 3 - SITE OPS'!I29 -> TRUE
A18: TI | C18: 02-4100.002 | D18: Demolition | F18: 1 | G18: ls | H18: ='STEP 3 - SITE OPS'!I35 -> 0 | I18: =IF(ISNUMBER(F18), F18 * H18, 0) -> 0 | J18: =IF($J$8=0, 0, I18/$J$8) -> 0 | K18: =IF($K$8=0, 0, I18/$K$8) -> 0 | S18: =I18='STEP 3 - SITE OPS'!I35 -> TRUE
A19: TI | C19: 02-9005.003 | D19: Final Cleaning | F19: 1 | G19: ls | H19: ='STEP 3 - SITE OPS'!I38 -> 0 | I19: =IF(ISNUMBER(F19), F19 * H19, 0) -> 0 | J19: =IF($J$8=0, 0, I19/$J$8) -> 0 | K19: =IF($K$8=0, 0, I19/$K$8) -> 0 | S19: ='STEP 4 - ESTIMATE'!I19='STEP 3 - SITE OPS'!I40 -> TRUE
C20: 02-9070.004 | D20: SWPPP Permit | F20: 1 | G20: ls | H20: ='STEP 3 - SITE OPS'!I43 -> 0 | I20: =IF(ISNUMBER(F20), F20 * H20, 0) -> 0 | J20: =IF($J$8=0, 0, I20/$J$8) -> 0 | K20: =IF($K$8=0, 0, I20/$K$8) -> 0 | S20: =I20='STEP 3 - SITE OPS'!I45 -> TRUE
C21: 02-9200.005 | D21: Survey and Layout | F21: 1 | G21: ls | H21: ='STEP 3 - SITE OPS'!I51 -> 0 | I21: =IF(ISNUMBER(F21), F21 * H21, 0) -> 0 | J21: =IF($J$8=0, 0, I21/$J$8) -> 0 | K21: =IF($K$8=0, 0, I21/$K$8) -> 0 | S21: ='STEP 4 - ESTIMATE'!I21='STEP 3 - SITE OPS'!I51 -> TRUE
C22: 02-9300.006 | D22: Building and Site Services | F22: 1 | G22: ls | H22: ='STEP 3 - SITE OPS'!I62 -> 0 | I22: =IF(ISNUMBER(F22), F22 * H22, 0) -> 0 | J22: =IF($J$8=0, 0, I22/$J$8) -> 0 | K22: =IF($K$8=0, 0, I22/$K$8) -> 0 | S22: =I22='STEP 3 - SITE OPS'!I62 -> TRUE
A23: TI | C23: 02-9400.007 | D23: Site Equipment | F23: 1 | G23: ls | H23: ='STEP 3 - SITE OPS'!I72 -> 0 | I23: =IF(ISNUMBER(F23), F23 * H23, 0) -> 0 | J23: =IF($J$8=0, 0, I23/$J$8) -> 0 | K23: =IF($K$8=0, 0, I23/$K$8) -> 0 | S23: =I23='STEP 3 - SITE OPS'!I72 -> TRUE
C24: 02-9500.008 | D24: Special Inspections | F24: 1 | G24: ls | H24: ='STEP 3 - SITE OPS'!I81 -> 0 | I24: =IF(ISNUMBER(F24), F24 * H24, 0) -> 0 | J24: =IF($J$8=0, 0, I24/$J$8) -> 0 | K24: =IF($K$8=0, 0, I24/$K$8) -> 0 | S24: =I24='STEP 3 - SITE OPS'!I82 -> TRUE
A25: TI
A26: TI | C26: DIVISION 03 — CONCRETE | D26: CONCRETE | E26: =SUM(I27:I52) -> 0
A27: TI
D28: CONCRETE
C29: 03-0000.001 | D29: Cast In-Place Concrete | F29: 0 | G29: ls | H29: 1 | I29: =IF(ISNUMBER(F29), F29 * H29, 0) -> 0 | J29: =IF($J$8=0, 0, I29/$J$8) -> 0 | K29: =IF($K$8=0, 0, I29/$K$8) -> 0
C30: 03-0000.002 | D30: Footings | F30: 0 | G30: cy | H30: 575 | I30: =IF(ISNUMBER(F30), F30 * H30, 0) -> 0 | J30: =IF($J$8=0, 0, I30/$J$8) -> 0 | K30: =IF($K$8=0, 0, I30/$K$8) -> 0
C31: 03-0000.003 | D31: Concrete Strip Footing | F31: 0 | G31: lf | H31: 55 | I31: =IF(ISNUMBER(F31), F31 * H31, 0) -> 0 | J31: =IF($J$8=0, 0, I31/$J$8) -> 0 | K31: =IF($K$8=0, 0, I31/$K$8) -> 0
C32: 03-0000.004 | D32: Concrete Fnd Pads | F32: 0 | G32: ea | H32: 4000 | I32: =IF(ISNUMBER(F32), F32 * H32, 0) -> 0 | J32: =IF($J$8=0, 0, I32/$J$8) -> 0 | K32: =IF($K$8=0, 0, I32/$K$8) -> 0
C33: 03-0000.005 | D33: Concrete Walls | F33: 0 | G33: sf | H33: 33 | I33: =IF(ISNUMBER(F33), F33 * H33, 0) -> 0 | J33: =IF($J$8=0, 0, I33/$J$8) -> 0 | K33: =IF($K$8=0, 0, I33/$K$8) -> 0
C34: 03-0000.006 | D34: Concrete Columns | F34: 0 | G34: ea | H34: 1000 | I34: =IF(ISNUMBER(F34), F34 * H34, 0) -> 0 | J34: =IF($J$8=0, 0, I34/$J$8) -> 0 | K34: =IF($K$8=0, 0, I34/$K$8) -> 0
C35: 03-0000.007 | D35: SOG | F35: 0 | G35: sf | H35: 7 | I35: =IF(ISNUMBER(F35), F35 * H35, 0) -> 0 | J35: =IF($J$8=0, 0, I35/$J$8) -> 0 | K35: =IF($K$8=0, 0, I35/$K$8) -> 0
C36: 03-0000.008 | D36: Under-Slab Insulation | F36: 0 | G36: sf | H36: 2 | I36: =IF(ISNUMBER(F36), F36 * H36, 0) -> 0 | J36: =IF($J$8=0, 0, I36/$J$8) -> 0 | K36: =IF($K$8=0, 0, I36/$K$8) -> 0
C37: 03-0000.009 | D37: Topping Slab on Precast Parking | F37: 0 | G37: sf | H37: 6 | I37: =IF(ISNUMBER(F37), F37 * H37, 0) -> 0 | J37: =IF($J$8=0, 0, I37/$J$8) -> 0 | K37: =IF($K$8=0, 0, I37/$K$8) -> 0
C38: 03-0000.010 | D38: Amenity Deck Topping Slab and Finished Slab | F38: 0 | G38: sf | H38: 6 | I38: =IF(ISNUMBER(F38), F38 * H38, 0) -> 0 | J38: =IF($J$8=0, 0, I38/$J$8) -> 0 | K38: =IF($K$8=0, 0, I38/$K$8) -> 0
C39: 03-0000.011 | D39: Post Tension Concrete | F39: 0 | G39: cy | H39: 400 | I39: =IF(ISNUMBER(F39), F39 * H39, 0) -> 0 | J39: =IF($J$8=0, 0, I39/$J$8) -> 0 | K39: =IF($K$8=0, 0, I39/$K$8) -> 0
C40: 03-0000.012 | D40: Concrete Patios | F40: 0 | G40: sf | H40: 7 | I40: =IF(ISNUMBER(F40), F40 * H40, 0) -> 0 | J40: =IF($J$8=0, 0, I40/$J$8) -> 0 | K40: =IF($K$8=0, 0, I40/$K$8) -> 0
A42: TI | D42: POLISHED CONCRETE
A43: TI | C43: 03-3543.001 | D43: Polished Concrete | F43: 0 | G43: sf | H43: 4 | I43: =IF(ISNUMBER(F43), F43 * H43, 0) -> 0 | J43: =IF($J$8=0, 0, I43/$J$8) -> 0 | K43: =IF($K$8=0, 0, I43/$K$8) -> 0
D45: PRECAST CONCRETE
C46: 03-4100.001 | D46: Precast Structural Concrete | F46: 0 | G46: sf | H46: 32 | I46: =IF(ISNUMBER(F46), F46 * H46, 0) -> 0 | J46: =IF($J$8=0, 0, I46/$J$8) -> 0 | K46: =IF($K$8=0, 0, I46/$K$8) -> 0
C47: 03-4500.0002 | D47: Precast Architectural Concrete | F47: 0 | G47: sf | H47: 55 | I47: =IF(ISNUMBER(F47), F47 * H47, 0) -> 0 | J47: =IF($J$8=0, 0, I47/$J$8) -> 0 | K47: =IF($K$8=0, 0, I47/$K$8) -> 0
D49: GYPSUM CEMENT UNDERLAYMENT
C50: 03-5413.001 | D50: Gypsum Cement Underlayment | F50: 0 | G50: sf | H50: 2 | I50: =IF(ISNUMBER(F50), F50 * H50, 0) -> 0 | J50: =IF($J$8=0, 0, I50/$J$8) -> 0 | K50: =IF($K$8=0, 0, I50/$K$8) -> 0
C51: 03-5413.002 | D51: Gypsum Cement (Subtract Podium Level If Pt) | F51: 0 | G51: sf | H51: =-H50 -> -2 | I51: =IF(ISNUMBER(F51), F51 * H51, 0) -> 0 | J51: =IF($J$8=0, 0, I51/$J$8) -> 0 | K51: =IF($K$8=0, 0, I51/$K$8) -> 0
A52: TI
A53: TI | C53: DIVISION 04 — MASONRY | D53: MASONRY | E53: =SUM(I54:I62) -> 0
A54: TI
C55: 04-0000.001 | D55: Masonry | F55: 0 | G55: ls | H55: 0 | I55: =IF(ISNUMBER(F55), F55 * H55, 0) -> 0 | J55: =IF($J$8=0, 0, I55/$J$8) -> 0 | K55: =IF($K$8=0, 0, I55/$K$8) -> 0
C56: 04-0000.002 | D56: Masonry - CMU Backup Around Building | F56: 0 | G56: sf | H56: 25 | I56: =IF(ISNUMBER(F56), F56 * H56, 0) -> 0 | J56: =IF($J$8=0, 0, I56/$J$8) -> 0 | K56: =IF($K$8=0, 0, I56/$K$8) -> 0
C57: 04-0000.003 | D57: Masonry - CMU In Garage | F57: 0 | G57: sf | H57: 25 | I57: =IF(ISNUMBER(F57), F57 * H57, 0) -> 0 | J57: =IF($J$8=0, 0, I57/$J$8) -> 0 | K57: =IF($K$8=0, 0, I57/$K$8) -> 0
C58: 04-0000.004 | D58: Masonry - Modular Brick Veneer | F58: 0 | G58: sf | H58: 60 | I58: =IF(ISNUMBER(F58), F58 * H58, 0) -> 0 | J58: =IF($J$8=0, 0, I58/$J$8) -> 0 | K58: =IF($K$8=0, 0, I58/$K$8) -> 0
A59: TI | C59: 04-0000.005 | D59: Masonry - Thin Brick | F59: 0 | G59: sf | H59: 25 | I59: =IF(ISNUMBER(F59), F59 * H59, 0) -> 0 | J59: =IF($J$8=0, 0, I59/$J$8) -> 0 | K59: =IF($K$8=0, 0, I59/$K$8) -> 0
C60: 04-0000.006 | D60: Masonry - Arriscraft | F60: 0 | G60: sf | H60: 95 | I60: =IF(ISNUMBER(F60), F60 * H60, 0) -> 0 | J60: =IF($J$8=0, 0, I60/$J$8) -> 0 | K60: =IF($K$8=0, 0, I60/$K$8) -> 0
C61: 04-0000.007 | D61: Masonry - PC Sill | F61: 0 | G61: lf | H61: 50 | I61: =IF(ISNUMBER(F61), F61 * H61, 0) -> 0 | J61: =IF($J$8=0, 0, I61/$J$8) -> 0 | K61: =IF($K$8=0, 0, I61/$K$8) -> 0
A62: TI
A63: TI | C63: DIVISION 05 — METALS | D63: METALS | E63: =SUM(I64:I72) -> 0
A64: TI
C65: 05-1200.001 | D65: Structural Steel | F65: 0 | G65: sf | H65: 55 | I65: =IF(ISNUMBER(F65), F65 * H65, 0) -> 0 | J65: =IF($J$8=0, 0, I65/$J$8) -> 0 | K65: =IF($K$8=0, 0, I65/$K$8) -> 0
A66: TI | C66: 05-5000.001 | D66: Metal Fabrications | F66: 0 | G66: ls | H66: 10 | I66: =IF(ISNUMBER(F66), F66 * H66, 0) -> 0 | J66: =IF($J$8=0, 0, I66/$J$8) -> 0 | K66: =IF($K$8=0, 0, I66/$K$8) -> 0
C67: 05-7210.001 | D67: Aluminum Decks | F67: 0 | G67: ea | H67: 3500 | I67: =IF(ISNUMBER(F67), F67 * H67, 0) -> 0 | J67: =IF($J$8=0, 0, I67/$J$8) -> 0 | K67: =IF($K$8=0, 0, I67/$K$8) -> 0
C68: 05-7210.002 | D68: Aluminum Decks - Juliette | F68: 0 | G68: ea | H68: 2400 | I68: =IF(ISNUMBER(F68), F68 * H68, 0) -> 0 | J68: =IF($J$8=0, 0, I68/$J$8) -> 0 | K68: =IF($K$8=0, 0, I68/$K$8) -> 0
C69: 05-7210.003 | D69: Aluminum Decks - Railing Only Balcony | F69: 0 | G69: ea | H69: 1000 | I69: =IF(ISNUMBER(F69), F69 * H69, 0) -> 0 | J69: =IF($J$8=0, 0, I69/$J$8) -> 0 | K69: =IF($K$8=0, 0, I69/$K$8) -> 0
C70: 05-7210.004 | D70: Aluminum Railings - F&I | F70: 0 | G70: lf | H70: 150 | I70: =IF(ISNUMBER(F70), F70 * H70, 0) -> 0 | J70: =IF($J$8=0, 0, I70/$J$8) -> 0 | K70: =IF($K$8=0, 0, I70/$K$8) -> 0
C71: 05-7210.005 | D71: Aluminum Decks And Railings - Installation | F71: 0 | G71: ea | H71: 800 | I71: =IF(ISNUMBER(F71), F71 * H71, 0) -> 0 | J71: =IF($J$8=0, 0, I71/$J$8) -> 0 | K71: =IF($K$8=0, 0, I71/$K$8) -> 0
A72: TI
A73: TI | C73: DIVISION 06 — WOOD, PLASTICS, COMPOSITES | E73: =SUM(I74:I92) -> 0
A74: TI
A75: TI | D75: ROUGH CARPENTRY
A76: TI | C76: 06-1000.001 | D76: Rough Carpentry Materials (Loose and Joists) | F76: 0 | G76: sf | H76: 13 | I76: =IF(ISNUMBER(F76), F76 * H76, 0) -> 0 | J76: =IF($J$8=0, 0, I76/$J$8) -> 0 | K76: =IF($K$8=0, 0, I76/$K$8) -> 0
A77: TI | C77: 06-1010.001 | D77: Rough Carpentry Installation | F77: 0 | G77: sf | H77: 7 | I77: =IF(ISNUMBER(F77), F77 * H77, 0) -> 0 | J77: =IF($J$8=0, 0, I77/$J$8) -> 0 | K77: =IF($K$8=0, 0, I77/$K$8) -> 0
C78: 06-1710.001 | D78: Manufactured Wall Panels | F78: 0 | G78: ls | H78: 0.001 | I78: =IF(ISNUMBER(F78), F78 * H78, 0) -> 0 | J78: =IF($J$8=0, 0, I78/$J$8) -> 0 | K78: =IF($K$8=0, 0, I78/$K$8) -> 0
C79: 06-1753.001 | D79: Shop-Fabricated Wood Trusses | F79: 0 | G79: ls | H79: 0.001 | I79: =IF(ISNUMBER(F79), F79 * H79, 0) -> 0 | J79: =IF($J$8=0, 0, I79/$J$8) -> 0 | K79: =IF($K$8=0, 0, I79/$K$8) -> 0
C80: 06-1800.001 | D80: Glu-Laminated Construction | F80: 0 | G80: ls | H80: 0 | I80: =IF(ISNUMBER(F80), F80 * H80, 0) -> 0 | J80: =IF($J$8=0, 0, I80/$J$8) -> 0 | K80: =IF($K$8=0, 0, I80/$K$8) -> 0
A81: TI | C81: 06-2000.001 | D81: Finish Carpentry Installation | F81: 0 | G81: ea | H81: 3600 | I81: =IF(ISNUMBER(F81), F81 * H81, 0) -> 0 | J81: =IF($J$8=0, 0, I81/$J$8) -> 0 | K81: =IF($K$8=0, 0, I81/$K$8) -> 0
A82: TI | C82: 06-2000.002 | D82: Finish Carpentry Installation - Doors | F82: 0 | G82: ea | H82: 450 | I82: =IF(ISNUMBER(F82), F82 * H82, 0) -> 0 | J82: =IF($J$8=0, 0, I82/$J$8) -> 0 | K82: =IF($K$8=0, 0, I82/$K$8) -> 0
A83: TI | C83: 06-2200.003 | D83: Millwork | F83: 0 | G83: ea | H83: 986 | I83: =IF(ISNUMBER(F83), F83 * H83, 0) -> 0 | J83: =IF($J$8=0, 0, I83/$J$8) -> 0 | K83: =IF($K$8=0, 0, I83/$K$8) -> 0
A84: TI | C84: 06-4100.001 | D84: Architectural Casework and Millwork | F84: 0 | G84: ls | H84: 0 | I84: =IF(ISNUMBER(F84), F84 * H84, 0) -> 0 | J84: =IF($J$8=0, 0, I84/$J$8) -> 0 | K84: =IF($K$8=0, 0, I84/$K$8) -> 0
A85: TI | C85: 06-6113.001 | D85: Simulated Stone Fabrications | F85: 0 | G85: ls | H85: 0 | I85: =IF(ISNUMBER(F85), F85 * H85, 0) -> 0 | J85: =IF($J$8=0, 0, I85/$J$8) -> 0 | K85: =IF($K$8=0, 0, I85/$K$8) -> 0
A86: TI | C86: 06-6116.001 | D86: Solid Surfacing And Ctops | F86: 0 | G86: ls | H86: 0 | I86: =IF(ISNUMBER(F86), F86 * H86, 0) -> 0 | J86: =IF($J$8=0, 0, I86/$J$8) -> 0 | K86: =IF($K$8=0, 0, I86/$K$8) -> 0
A87: TI | C87: 06-8316.001 | D87: FRP Wall Paneling | F87: 0 | G87: ls | H87: 0 | I87: =IF(ISNUMBER(F87), F87 * H87, 0) -> 0 | J87: =IF($J$8=0, 0, I87/$J$8) -> 0 | K87: =IF($K$8=0, 0, I87/$K$8) -> 0
A88: TI
D89: PERGOLAS AND COMPOSITE
C90: 06-7300.001 | D90: Composite Decking | F90: 0 | G90: ea | H90: 1200 | I90: =IF(ISNUMBER(F90), F90 * H90, 0) -> 0 | J90: =IF($J$8=0, 0, I90/$J$8) -> 0 | K90: =IF($K$8=0, 0, I90/$K$8) -> 0
C91: 06-8700.001 | D91: Pergolas | F91: 0 | G91: ea | H91: 15000 | I91: =IF(ISNUMBER(F91), F91 * H91, 0) -> 0 | J91: =IF($J$8=0, 0, I91/$J$8) -> 0 | K91: =IF($K$8=0, 0, I91/$K$8) -> 0
A93: TI | C93: DIVISION 07 — THERMAL & MOISTURE PROTECTION | D93: CONCRETE | E93: =SUM(I94:I130) -> 0
A94: TI
D95: WATERPROOFING AND AIR BARRIERS
C96: 07-1000.001 | D96: Waterproofing | F96: 0 | G96: sf | H96: 7 | I96: =IF(ISNUMBER(F96), F96 * H96, 0) -> 0 | J96: =IF($J$8=0, 0, I96/$J$8) -> 0 | K96: =IF($K$8=0, 0, I96/$K$8) -> 0
C97: 07-1000.002 | D97: Elevator Waterproofing | F97: 0 | G97: ea | H97: 5500 | I97: =IF(ISNUMBER(F97), F97 * H97, 0) -> 0 | J97: =IF($J$8=0, 0, I97/$J$8) -> 0 | K97: =IF($K$8=0, 0, I97/$K$8) -> 0
C98: 07-1413.001 | D98: Hot-Fluid-Applied Waterproofing | F98: 0 | G98: sf | H98: 8 | I98: =IF(ISNUMBER(F98), F98 * H98, 0) -> 0 | J98: =IF($J$8=0, 0, I98/$J$8) -> 0 | K98: =IF($K$8=0, 0, I98/$K$8) -> 0
C99: 07-1413.002 | D99: Per 2" Insulation | F99: 0 | G99: sf | H99: 2 | I99: =IF(ISNUMBER(F99), F99 * H99, 0) -> 0 | J99: =IF($J$8=0, 0, I99/$J$8) -> 0 | K99: =IF($K$8=0, 0, I99/$K$8) -> 0
C100: 07-1413.003 | D100: Patios | F100: 0 | G100: sf | H100: 0 | I100: =IF(ISNUMBER(F100), F100 * H100, 0) -> 0 | J100: =IF($J$8=0, 0, I100/$J$8) -> 0 | K100: =IF($K$8=0, 0, I100/$K$8) -> 0
C101: 07-1413.004 | D101: Sky Deck | F101: 0 | G101: sf | H101: 0 | I101: =IF(ISNUMBER(F101), F101 * H101, 0) -> 0 | J101: =IF($J$8=0, 0, I101/$J$8) -> 0 | K101: =IF($K$8=0, 0, I101/$K$8) -> 0
C102: 07-1413.005 | D102: Restaurant / Commercial Patios | F102: 0 | G102: sf | H102: 0 | I102: =IF(ISNUMBER(F102), F102 * H102, 0) -> 0 | J102: =IF($J$8=0, 0, I102/$J$8) -> 0 | K102: =IF($K$8=0, 0, I102/$K$8) -> 0
C103: 07-1800.001 | D103: Traffic Coatings | F103: 0 | G103: sf | H103: 8 | I103: =IF(ISNUMBER(F103), F103 * H103, 0) -> 0 | J103: =IF($J$8=0, 0, I103/$J$8) -> 0 | K103: =IF($K$8=0, 0, I103/$K$8) -> 0
A105: TI | D105: THERMAL PROTECTION
A106: TI | C106: 07-2100.001 | D106: Thermal Insulation | F106: 0 | G106: ea | H106: 3200 | I106: =IF(ISNUMBER(F106), F106 * H106, 0) -> 0 | J106: =IF($J$8=0, 0, I106/$J$8) -> 0 | K106: =IF($K$8=0, 0, I106/$K$8) -> 0
...

Sheet VEs_ALTS_MF
C2: ='STEP 1 - PROJECT DATA'!D6& "." & 'STEP 1 - PROJECT DATA'!D7 -> E26-123.0
C3: ='STEP 1 - PROJECT DATA'!C5 -> Project Name | D3: ='STEP 1 - PROJECT DATA'!D5 -> Name | E3: Value Engineering / Project Alternates | K3: Date | L3: ='STEP 1 - PROJECT DATA'!G9 -> 46010
C4: Location | D4: ='STEP 1 - PROJECT DATA'!D8 -> 1234 Main St | K4: Pricing Legend
D5: ='STEP 1 - PROJECT DATA'!D9 -> Minneapolis, MN | K5: P | L5: = Preliminary
C6: ='STEP 1 - PROJECT DATA'!C13 -> Architect | D6: ='STEP 1 - PROJECT DATA'!D13 -> TBD | K6: A | L6: = Allowance
C7: ='STEP 1 - PROJECT DATA'!C14 -> Plan Set | D7: ='STEP 1 - PROJECT DATA'!D14 -> TBD | K7: C | L7: = Confirmed
D9: Description | E9: Estimated Cost | F9: Pricing Type | G9: Accepted (In Estimate) | H9: Accepted (Pending Estimate) | I9: Pending | J9: Rejected | K9: Ball-in-Court | L9: Comments
C10: Alternate 01: | D10: GENERAL CONDITIONS | E10: =SUM(E11:E15) -> 2700
C11: 1.1 | D11: Example | E11: 1500 | F11: P | G11: =$E$11 -> 1500 | L11: Notes
C12: 1.2 | D12: 2 | E12: 100 | G12: =$E$12 -> 100
C13: 1.3 | D13: 3 | E13: 500 | G13: =$E$13 -> 500
C14: 1.4 | D14: 4 | E14: 600 | G14: =$E$14 -> 600
C15: 1.5 | E15: 0 | I15: =$E$15 -> 0
C16: Alternate 02: | D16: GENERAL CONDITIONS
C17: =C11+1 -> 2.1 | E17: 0
C18: =C17+0.1 -> 2.2 | E18: 0
C19: =C18+0.1 -> 2.3 | E19: 0
C20: =C19+0.1 -> 2.4 | E20: 0
C21: =C20+0.1 -> 2.5 | E21: 0
C22: Alternate 03: | D22: GENERAL CONDITIONS
C23: =C17+1 -> 3.1 | E23: 0
C24: =C23+0.1 -> 3.2 | E24: 0
C25: =C24+0.1 -> 3.3 | E25: 0
C26: =C25+0.1 -> 3.4 | E26: 0
C27: =C26+0.1 -> 3.5 | E27: 0
C28: Alternate 04: | D28: GENERAL CONDITIONS
C29: =C23+1 -> 4.1 | E29: 0
C30: =C29+0.1 -> 4.2 | E30: 0
C31: =C30+0.1 -> 4.3 | E31: 0
C32: =C31+0.1 -> 4.4 | E32: 0
C33: =C32+0.1 -> 4.5 | E33: 0
C34: DIVISION 05 — METALS | D34: METALS
C35: =C29+1 -> 5.1 | E35: 0
C36: =C35+0.1 -> 5.2 | E36: 0
C37: =C36+0.1 -> 5.3 | E37: 0
C38: =C37+0.1 -> 5.4 | E38: 0
C39: =C38+0.1 -> 5.5 | E39: 0
C40: DIVISION 06 — WOOD, PLASTICS, AND COMPOSITES
C41: =C35+1 -> 6.1 | E41: 0
C42: =C41+0.1 -> 6.2 | E42: 0
C43: =C42+0.1 -> 6.3 | E43: 0
C44: =C43+0.1 -> 6.4 | E44: 0
C45: =C44+0.1 -> 6.5 | E45: 0
C46: DIVISION 07 — THERMAL AND MOISTURE PROTECTION
C47: =C41+1 -> 7.1 | E47: 0
C48: =C47+0.1 -> 7.2 | E48: 0
C49: =C48+0.1 -> 7.3 | E49: 0
C50: =C49+0.1 -> 7.4 | E50: 0
C51: =C50+0.1 -> 7.5 | E51: 0
C52: DIVISION 08 — OPENINGS | D52: CONCRETE
C53: =C47+1 -> 8.1 | E53: 0
C54: =C53+0.1 -> 8.2 | E54: 0
C55: =C54+0.1 -> 8.3 | E55: 0
C56: =C55+0.1 -> 8.4 | E56: 0
C57: =C56+0.1 -> 8.5 | E57: 0
C58: DIVISION 09 — FINISHES | D58: PARTITIONS & FINISHES
C59: =C53+1 -> 9.1 | E59: 0
C60: =C59+0.1 -> 9.2 | E60: 0
C61: =C60+0.1 -> 9.3 | E61: 0
C62: =C61+0.1 -> 9.4 | E62: 0
C63: =C62+0.1 -> 9.5 | E63: 0
C64: DIVISION 10 — SPECIALTIES | D64: PARTITIONS & FINISHES
C65: =C59+1 -> 10.1 | E65: 0
C66: =C65+0.1 -> 10.2 | E66: 0
C67: =C66+0.1 -> 10.3 | E67: 0
C68: =C67+0.1 -> 10.4 | E68: 0
C69: =C68+0.1 -> 10.5 | E69: 0
C70: DIVISION 11 — EQUIPMENT | D70: PARTITIONS & FINISHES
C71: =C65+1 -> 11.1 | E71: 0
C72: =C71+0.1 -> 11.2 | E72: 0
C73: =C72+0.1 -> 11.3 | E73: 0
C74: =C73+0.1 -> 11.4 | E74: 0
C75: =C74+0.1 -> 11.5 | E75: 0
C76: DIVISION 12 — FURNISHINGS | D76: PARTITIONS & FINISHES
C77: =C71+1 -> 12.1 | E77: 0
C78: =C77+0.1 -> 12.2 | E78: 0
C79: =C78+0.1 -> 12.3 | E79: 0
C80: =C79+0.1 -> 12.4 | E80: 0
C81: =C80+0.1 -> 12.5 | E81: 0
C82: DIVISION 13 — SPECIAL CONSTRUCTION
C83: =C77+1 -> 13.1 | E83: 0
C84: =C83+0.1 -> 13.2 | E84: 0
C85: =C84+0.1 -> 13.3 | E85: 0
C86: =C85+0.1 -> 13.4 | E86: 0
C87: =C86+0.1 -> 13.5 | E87: 0
C88: DIVISION 14 — CONVEYING EQUIPMENT
C89: =C83+1 -> 14.1 | E89: 0
C90: =C89+0.1 -> 14.2 | E90: 0
C91: =C90+0.1 -> 14.3 | E91: 0
C92: =C91+0.1 -> 14.4 | E92: 0
C93: =C92+0.1 -> 14.5 | E93: 0
C94: DIVISION 21 — FIRE SUPPRESSION
C95: 21.1 | E95: 0
C96: =C95+0.1 -> 21.2 | E96: 0
C97: =C96+0.1 -> 21.3 | E97: 0
C98: =C97+0.1 -> 21.4 | E98: 0
C99: =C98+0.1 -> 21.5 | E99: 0
C100: DIVISION 22 — PLUMBING
C101: 22.1 | E101: 0
C102: =C101+0.1 -> 22.2 | E102: 0
...

Sheet VEs_ALTS_COMMERCIAL 
C2: ='STEP 1 - PROJECT DATA'!D6& "." & 'STEP 1 - PROJECT DATA'!D7 -> E26-123.0
D3: Value Engineering / Project Alternates
M4: Alt Markup % | N4: 0.1
D9: Description | E9: Comments | F9: Total | J9: Vendor | K9: Description | L9: Comments | M9: Vendor Cost | N9: Total
A10: =IF(F10<>0,1,0) -> 0 | C10: =J10 -> Alternate 01: | F10: =F15 -> 0 | J10: Alternate 01:
A11: =IF(F11<>0,1,0) -> 0 | D11: =IF(K11=0," ",K11) | F11: =N11 -> 0 | M11: 0 | N11: =M11*1+M11*$N$4 -> 0
A12: =IF(F12<>0,1,0) -> 0 | D12: =IF(K12=0," ",K12) | F12: =N12 -> 0 | M12: 0 | N12: =M12*1+M12*$N$4 -> 0
A13: =IF(F13<>0,1,0) -> 0 | D13: =IF(K13=0," ",K13) | F13: =N13 -> 0 | M13: 0 | N13: =M13*1+M13*$N$4 -> 0
A14: =IF(F14<>0,1,0) -> 0 | D14: =IF(K14=0," ",K14) | F14: =N14 -> 0 | M14: 0 | N14: =M14*1+M14*$N$4 -> 0
A15: =IF(F15<>0,1,0) -> 0 | C15: Total: | D15: =IF(K15=0," ",K15) | F15: =N15 -> 0 | J15: Total: | M15: =SUM(M11:M14) -> 0 | N15: =SUM(N11:N14) -> 0
A16: =IF(F16<>0,1,0) -> 0 | C16: =J16 -> Alternate 02: | F16: =F21 -> 0 | J16: Alternate 02:
A17: =IF(F17<>0,1,0) -> 0 | D17: =IF(K17=0," ",K17) | F17: =N17 -> 0 | M17: 0 | N17: =M17*1+M17*$N$4 -> 0
A18: =IF(F18<>0,1,0) -> 0 | D18: =IF(K18=0," ",K18) | F18: =N18 -> 0 | M18: 0 | N18: =M18*1+M18*$N$4 -> 0
A19: =IF(F19<>0,1,0) -> 0 | D19: =IF(K19=0," ",K19) | F19: =N19 -> 0 | M19: 0 | N19: =M19*1+M19*$N$4 -> 0
A20: =IF(F20<>0,1,0) -> 0 | D20: =IF(K20=0," ",K20) | F20: =N20 -> 0 | M20: 0 | N20: =M20*1+M20*$N$4 -> 0
A21: =IF(F21<>0,1,0) -> 0 | C21: Total: | D21: =IF(K21=0," ",K21) | F21: =N21 -> 0 | J21: Total: | M21: =SUM(M17:M20) -> 0 | N21: =SUM(N17:N20) -> 0
A22: =IF(F22<>0,1,0) -> 1 | C22: =J22 -> Alternate 03: | F22: =F27 -> 551.1 | J22: Alternate 03:
A23: =IF(F23<>0,1,0) -> 1 | D23: =IF(K23=0," ",K23) | F23: =N23 -> 550 | M23: 500 | N23: =M23*1+M23*$N$4 -> 550
A24: =IF(F24<>0,1,0) -> 0 | D24: =IF(K24=0," ",K24) | F24: =N24 -> 0 | M24: 0 | N24: =M24*1+M24*$N$4 -> 0
A25: =IF(F25<>0,1,0) -> 0 | D25: =IF(K25=0," ",K25) | F25: =N25 -> 0 | M25: 0 | N25: =M25*1+M25*$N$4 -> 0
A26: =IF(F26<>0,1,0) -> 1 | D26: =IF(K26=0," ",K26) | F26: =N26 -> 1.1 | M26: 1 | N26: =M26*1+M26*$N$4 -> 1.1
A27: =IF(F27<>0,1,0) -> 1 | C27: Total: | D27: =IF(K27=0," ",K27) | F27: =N27 -> 551.1 | J27: Total: | M27: =SUM(M23:M26) -> 501 | N27: =SUM(N23:N26) -> 551.1
A28: =IF(F28<>0,1,0) -> 0 | C28: =J28 -> Alternate 04: | F28: =F33 -> 0 | J28: Alternate 04:
A29: =IF(F29<>0,1,0) -> 0 | D29: =IF(K29=0," ",K29) | F29: =N29 -> 0 | M29: 0 | N29: =M29*1+M29*$N$4 -> 0
A30: =IF(F30<>0,1,0) -> 0 | D30: =IF(K30=0," ",K30) | F30: =N30 -> 0 | M30: 0 | N30: =M30*1+M30*$N$4 -> 0
A31: =IF(F31<>0,1,0) -> 0 | D31: =IF(K31=0," ",K31) | F31: =N31 -> 0 | M31: 0 | N31: =M31*1+M31*$N$4 -> 0
A32: =IF(F32<>0,1,0) -> 0 | D32: =IF(K32=0," ",K32) | F32: =N32 -> 0 | M32: 0 | N32: =M32*1+M32*$N$4 -> 0
A33: =IF(F33<>0,1,0) -> 0 | C33: Total: | D33: =IF(K33=0," ",K33) | F33: =N33 -> 0 | J33: Total: | M33: =SUM(M29:M32) -> 0 | N33: =SUM(N29:N32) -> 0
A34: =IF(F34<>0,1,0) -> 0 | C34: =J34 -> Alternate 05: | F34: =F39 -> 0 | J34: Alternate 05:
A35: =IF(F35<>0,1,0) -> 0 | D35: =IF(K35=0," ",K35) | F35: =N35 -> 0 | M35: 0 | N35: =M35*1+M35*$N$4 -> 0
A36: =IF(F36<>0,1,0) -> 0 | D36: =IF(K36=0," ",K36) | F36: =N36 -> 0 | M36: 0 | N36: =M36*1+M36*$N$4 -> 0
A37: =IF(F37<>0,1,0) -> 0 | D37: =IF(K37=0," ",K37) | F37: =N37 -> 0 | M37: 0 | N37: =M37*1+M37*$N$4 -> 0
A38: =IF(F38<>0,1,0) -> 0 | D38: =IF(K38=0," ",K38) | F38: =N38 -> 0 | M38: 0 | N38: =M38*1+M38*$N$4 -> 0
A39: =IF(F39<>0,1,0) -> 0 | C39: Total: | D39: =IF(K39=0," ",K39) | F39: =N39 -> 0 | J39: Total: | M39: =SUM(M35:M38) -> 0 | N39: =SUM(N35:N38) -> 0
A40: =IF(F40<>0,1,0) -> 0 | C40: =J40 -> Alternate 06: | F40: =F45 -> 0 | J40: Alternate 06:
A41: =IF(F41<>0,1,0) -> 0 | D41: =IF(K41=0," ",K41) | F41: =N41 -> 0 | M41: 0 | N41: =M41*1+M41*$N$4 -> 0
A42: =IF(F42<>0,1,0) -> 0 | D42: =IF(K42=0," ",K42) | F42: =N42 -> 0 | M42: 0 | N42: =M42*1+M42*$N$4 -> 0
A43: =IF(F43<>0,1,0) -> 0 | D43: =IF(K43=0," ",K43) | F43: =N43 -> 0 | M43: 0 | N43: =M43*1+M43*$N$4 -> 0
A44: =IF(F44<>0,1,0) -> 0 | D44: =IF(K44=0," ",K44) | F44: =N44 -> 0 | M44: 0 | N44: =M44*1+M44*$N$4 -> 0
A45: =IF(F45<>0,1,0) -> 0 | C45: Total: | D45: =IF(K45=0," ",K45) | F45: =N45 -> 0 | J45: Total: | M45: =SUM(M41:M44) -> 0 | N45: =SUM(N41:N44) -> 0
A46: =IF(F46<>0,1,0) -> 0 | C46: =J46 -> Alternate 07: | F46: =F51 -> 0 | J46: Alternate 07:
A47: =IF(F47<>0,1,0) -> 0 | D47: =IF(K47=0," ",K47) | F47: =N47 -> 0 | M47: 0 | N47: =M47*1+M47*$N$4 -> 0
A48: =IF(F48<>0,1,0) -> 0 | D48: =IF(K48=0," ",K48) | F48: =N48 -> 0 | M48: 0 | N48: =M48*1+M48*$N$4 -> 0
A49: =IF(F49<>0,1,0) -> 0 | D49: =IF(K49=0," ",K49) | F49: =N49 -> 0 | M49: 0 | N49: =M49*1+M49*$N$4 -> 0
A50: =IF(F50<>0,1,0) -> 0 | D50: =IF(K50=0," ",K50) | F50: =N50 -> 0 | M50: 0 | N50: =M50*1+M50*$N$4 -> 0
A51: =IF(F51<>0,1,0) -> 0 | C51: Total: | D51: =IF(K51=0," ",K51) | F51: =N51 -> 0 | J51: Total: | M51: =SUM(M47:M50) -> 0 | N51: =SUM(N47:N50) -> 0
A52: =IF(F52<>0,1,0) -> 0 | C52: =J52 -> Alternate 08: | F52: =F57 -> 0 | J52: Alternate 08:
A53: =IF(F53<>0,1,0) -> 0 | D53: =IF(K53=0," ",K53) | F53: =N53 -> 0 | M53: 0 | N53: =M53*1+M53*$N$4 -> 0
A54: =IF(F54<>0,1,0) -> 0 | D54: =IF(K54=0," ",K54) | F54: =N54 -> 0 | M54: 0 | N54: =M54*1+M54*$N$4 -> 0
A55: =IF(F55<>0,1,0) -> 0 | D55: =IF(K55=0," ",K55) | F55: =N55 -> 0 | M55: 0 | N55: =M55*1+M55*$N$4 -> 0
A56: =IF(F56<>0,1,0) -> 0 | D56: =IF(K56=0," ",K56) | F56: =N56 -> 0 | M56: 0 | N56: =M56*1+M56*$N$4 -> 0
A57: =IF(F57<>0,1,0) -> 0 | C57: Total: | D57: =IF(K57=0," ",K57) | F57: =N57 -> 0 | J57: Total: | M57: =SUM(M53:M56) -> 0 | N57: =SUM(N53:N56) -> 0
A58: =IF(F58<>0,1,0) -> 0 | C58: =J58 -> Alternate 09: | F58: =F63 -> 0 | J58: Alternate 09:
A59: =IF(F59<>0,1,0) -> 0 | D59: =IF(K59=0," ",K59) | F59: =N59 -> 0 | M59: 0 | N59: =M59*1+M59*$N$4 -> 0
A60: =IF(F60<>0,1,0) -> 0 | D60: =IF(K60=0," ",K60) | F60: =N60 -> 0 | M60: 0 | N60: =M60*1+M60*$N$4 -> 0
A61: =IF(F61<>0,1,0) -> 0 | D61: =IF(K61=0," ",K61) | F61: =N61 -> 0 | M61: 0 | N61: =M61*1+M61*$N$4 -> 0
A62: =IF(F62<>0,1,0) -> 0 | D62: =IF(K62=0," ",K62) | F62: =N62 -> 0 | M62: 0 | N62: =M62*1+M62*$N$4 -> 0
A63: =IF(F63<>0,1,0) -> 0 | C63: Total: | D63: =IF(K63=0," ",K63) | F63: =N63 -> 0 | J63: Total: | M63: =SUM(M59:M62) -> 0 | N63: =SUM(N59:N62) -> 0
A64: =IF(F64<>0,1,0) -> 0 | C64: =J64 -> Alternate 10: | F64: =F69 -> 0 | J64: Alternate 10:
A65: =IF(F65<>0,1,0) -> 0 | D65: =IF(K65=0," ",K65) | F65: =N65 -> 0 | M65: 0 | N65: =M65*1+M65*$N$4 -> 0
A66: =IF(F66<>0,1,0) -> 0 | D66: =IF(K66=0," ",K66) | F66: =N66 -> 0 | M66: 0 | N66: =M66*1+M66*$N$4 -> 0
A67: =IF(F67<>0,1,0) -> 0 | D67: =IF(K67=0," ",K67) | F67: =N67 -> 0 | M67: 0 | N67: =M67*1+M67*$N$4 -> 0
A68: =IF(F68<>0,1,0) -> 0 | D68: =IF(K68=0," ",K68) | F68: =N68 -> 0 | M68: 0 | N68: =M68*1+M68*$N$4 -> 0
A69: =IF(F69<>0,1,0) -> 0 | C69: Total: | D69: =IF(K69=0," ",K69) | F69: =N69 -> 0 | J69: Total: | M69: =SUM(M65:M68) -> 0 | N69: =SUM(N65:N68) -> 0
A70: =IF(F70<>0,1,0) -> 0 | C70: =J70 -> Alternate 11: | F70: =F75 -> 0 | J70: Alternate 11:
A71: =IF(F71<>0,1,0) -> 0 | D71: =IF(K71=0," ",K71) | F71: =N71 -> 0 | M71: 0 | N71: =M71*1+M71*$N$4 -> 0
A72: =IF(F72<>0,1,0) -> 0 | D72: =IF(K72=0," ",K72) | F72: =N72 -> 0 | M72: 0 | N72: =M72*1+M72*$N$4 -> 0
A73: =IF(F73<>0,1,0) -> 0 | D73: =IF(K73=0," ",K73) | F73: =N73 -> 0 | M73: 0 | N73: =M73*1+M73*$N$4 -> 0
A74: =IF(F74<>0,1,0) -> 0 | D74: =IF(K74=0," ",K74) | F74: =N74 -> 0 | M74: 0 | N74: =M74*1+M74*$N$4 -> 0
A75: =IF(F75<>0,1,0) -> 0 | C75: Total: | D75: =IF(K75=0," ",K75) | F75: =N75 -> 0 | J75: Total: | M75: =SUM(M71:M74) -> 0 | N75: =SUM(N71:N74) -> 0
A76: =IF(F76<>0,1,0) -> 0 | C76: =J76 -> Alternate 12: | F76: =F81 -> 0 | J76: Alternate 12:
A77: =IF(F77<>0,1,0) -> 0 | D77: =IF(K77=0," ",K77) | F77: =N77 -> 0 | M77: 0 | N77: =M77*1+M77*$N$4 -> 0
A78: =IF(F78<>0,1,0) -> 0 | D78: =IF(K78=0," ",K78) | F78: =N78 -> 0 | M78: 0 | N78: =M78*1+M78*$N$4 -> 0
A79: =IF(F79<>0,1,0) -> 0 | D79: =IF(K79=0," ",K79) | F79: =N79 -> 0 | M79: 0 | N79: =M79*1+M79*$N$4 -> 0
A80: =IF(F80<>0,1,0) -> 0 | D80: =IF(K80=0," ",K80) | F80: =N80 -> 0 | M80: 0 | N80: =M80*1+M80*$N$4 -> 0
A81: =IF(F81<>0,1,0) -> 0 | C81: Total: | D81: =IF(K81=0," ",K81) | F81: =N81 -> 0 | J81: Total: | M81: =SUM(M77:M80) -> 0 | N81: =SUM(N77:N80) -> 0
A82: =IF(F82<>0,1,0) -> 0 | C82: =J82 -> Alternate 13: | F82: =F87 -> 0 | J82: Alternate 13:
A83: =IF(F83<>0,1,0) -> 0 | D83: =IF(K83=0," ",K83) | F83: =N83 -> 0 | M83: 0 | N83: =M83*1+M83*$N$4 -> 0
A84: =IF(F84<>0,1,0) -> 0 | D84: =IF(K84=0," ",K84) | F84: =N84 -> 0 | M84: 0 | N84: =M84*1+M84*$N$4 -> 0
A85: =IF(F85<>0,1,0) -> 0 | D85: =IF(K85=0," ",K85) | F85: =N85 -> 0 | M85: 0 | N85: =M85*1+M85*$N$4 -> 0
A86: =IF(F86<>0,1,0) -> 0 | D86: =IF(K86=0," ",K86) | F86: =N86 -> 0 | M86: 0 | N86: =M86*1+M86*$N$4 -> 0
A87: =IF(F87<>0,1,0) -> 0 | C87: Total: | D87: =IF(K87=0," ",K87) | F87: =N87 -> 0 | J87: Total: | M87: =SUM(M83:M86) -> 0 | N87: =SUM(N83:N86) -> 0
A88: =IF(F88<>0,1,0) -> 0 | C88: =J88 -> Alternate 14: | F88: =F93 -> 0 | J88: Alternate 14:
A89: =IF(F89<>0,1,0) -> 0 | D89: =IF(K89=0," ",K89) | F89: =N89 -> 0 | M89: 0 | N89: =M89*1+M89*$N$4 -> 0
A90: =IF(F90<>0,1,0) -> 0 | D90: =IF(K90=0," ",K90) | F90: =N90 -> 0 | M90: 0 | N90: =M90*1+M90*$N$4 -> 0
A91: =IF(F91<>0,1,0) -> 0 | D91: =IF(K91=0," ",K91) | F91: =N91 -> 0 | M91: 0 | N91: =M91*1+M91*$N$4 -> 0
A92: =IF(F92<>0,1,0) -> 0 | D92: =IF(K92=0," ",K92) | F92: =N92 -> 0 | M92: 0 | N92: =M92*1+M92*$N$4 -> 0
A93: =IF(F93<>0,1,0) -> 0 | C93: Total: | D93: =IF(K93=0," ",K93) | F93: =N93 -> 0 | J93: Total: | M93: =SUM(M89:M92) -> 0 | N93: =SUM(N89:N92) -> 0
A94: =IF(F94<>0,1,0) -> 0 | C94: =J94 -> Alternate 15: | F94: =F99 -> 0 | J94: Alternate 15:
A95: =IF(F95<>0,1,0) -> 0 | D95: =IF(K95=0," ",K95) | F95: =N95 -> 0 | M95: 0 | N95: =M95*1+M95*$N$4 -> 0
A96: =IF(F96<>0,1,0) -> 0 | D96: =IF(K96=0," ",K96) | F96: =N96 -> 0 | M96: 0 | N96: =M96*1+M96*$N$4 -> 0
A97: =IF(F97<>0,1,0) -> 0 | D97: =IF(K97=0," ",K97) | F97: =N97 -> 0 | M97: 0 | N97: =M97*1+M97*$N$4 -> 0
A98: =IF(F98<>0,1,0) -> 0 | D98: =IF(K98=0," ",K98) | F98: =N98 -> 0 | M98: 0 | N98: =M98*1+M98*$N$4 -> 0
A99: =IF(F99<>0,1,0) -> 0 | C99: Total: | D99: =IF(K99=0," ",K99) | F99: =N99 -> 0 | J99: Total: | M99: =SUM(M95:M98) -> 0 | N99: =SUM(N95:N98) -> 0
A100: =IF(F100<>0,1,0) -> 0 | C100: =J100 -> Alternate 16: | F100: =F105 -> 0 | J100: Alternate 16:
A101: =IF(F101<>0,1,0) -> 0 | D101: =IF(K101=0," ",K101) | F101: =N101 -> 0 | M101: 0 | N101: =M101*1+M101*$N$4 -> 0
A102: =IF(F102<>0,1,0) -> 0 | D102: =IF(K102=0," ",K102) | F102: =N102 -> 0 | M102: 0 | N102: =M102*1+M102*$N$4 -> 0
A103: =IF(F103<>0,1,0) -> 0 | D103: =IF(K103=0," ",K103) | F103: =N103 -> 0 | M103: 0 | N103: =M103*1+M103*$N$4 -> 0
A104: =IF(F104<>0,1,0) -> 0 | D104: =IF(K104=0," ",K104) | F104: =N104 -> 0 | M104: 0 | N104: =M104*1+M104*$N$4 -> 0
A105: =IF(F105<>0,1,0) -> 0 | C105: Total: | D105: =IF(K105=0," ",K105) | F105: =N105 -> 0 | J105: Total: | M105: =SUM(M101:M104) -> 0 | N105: =SUM(N101:N104) -> 0
...

Sheet WINTER CONDITIONS
C2: ='STEP 1 - PROJECT DATA'!D6& "." & 'STEP 1 - PROJECT DATA'!D7 -> E26-123.0
C3: ='STEP 1 - PROJECT DATA'!C5 -> Project Name | D3: ='STEP 1 - PROJECT DATA'!D5 -> Name | G3: Winter Conditions Estimate
C4: Location | D4: ='STEP 1 - PROJECT DATA'!D8 -> 1234 Main St
D5: ='STEP 1 - PROJECT DATA'!D9 -> Minneapolis, MN | E5: Actual | F5: Forecasted
C6: ='STEP 1 - PROJECT DATA'!C13 -> Architect | D6: ='STEP 1 - PROJECT DATA'!D13 -> TBD
C7: ='STEP 1 - PROJECT DATA'!C14 -> Plan Set | D7: ='STEP 1 - PROJECT DATA'!D14 -> TBD
E8: Season 1 | L8: Season 2
D9: Description | E9: Nov | F9: Dec | G9: Jan | H9: Feb | I9: Mar | J9: Apr | L9: Nov | M9: Dec | N9: Jan | O9: Feb | P9: Mar | Q9: Apr
C11: DIVISION 50 — WINTER CONDITIONS
E12: 0 | F12: 0 | G12: 0 | H12: 0 | I12: 0 | J12: 0 | L12: 0 | M12: 0 | N12: 0 | O12: 0 | P12: 0 | Q12: 0
C13: =C21+0.1 -> 50.2 | D13: Seasonal Rental Heaters | E13: 0 | F13: 0 | G13: 0 | H13: 0 | I13: 0 | J13: 0 | L13: 0 | M13: 0 | N13: 0 | O13: 0 | P13: 0 | Q13: 0
C14: =C17+0.1 -> 50.6 | D14: Rental Equipment | E14: 0 | F14: 0 | G14: 0 | H14: 0 | I14: 0 | J14: 0 | L14: 0 | M14: 0 | N14: 0 | O14: 0 | P14: 0 | Q14: 0
C15: =C13+0.1 -> 50.3 | D15: Plowing and Snow Removal | E15: 0 | F15: 0 | G15: 0 | H15: 0 | I15: 0 | J15: 0 | L15: 0 | M15: 0 | N15: 0 | O15: 0 | P15: 0 | Q15: 0
C16: =C15+0.1 -> 50.4 | D16: Concrete Subcontractor | E16: 0 | F16: 0 | G16: 0 | H16: 0 | I16: 0 | J16: 0 | L16: 0 | M16: 0 | N16: 0 | O16: 0 | P16: 0 | Q16: 0
C17: =C16+0.1 -> 50.5 | D17: Masonry Subcontractor | E17: 0 | F17: 0 | G17: 0 | H17: 0 | I17: 0 | J17: 0 | L17: 0 | M17: 0 | N17: 0 | O17: 0 | P17: 0 | Q17: 0
C18: =C12+0.1 -> 0.1 | D18: Mechanical Contractor | E18: 0 | F18: 0 | G18: 0 | H18: 0 | I18: 0 | J18: 0 | L18: 0 | M18: 0 | N18: 0 | O18: 0 | P18: 0 | Q18: 0
C19: 50.1 | D19: Earthwork Contractor | E19: 0 | F19: 0 | G19: 0 | H19: 0 | I19: 0 | J19: 0 | L19: 0 | M19: 0 | N19: 0 | O19: 0 | P19: 0 | Q19: 0
C20: =C14+0.1 -> 50.7 | D20: FP Labor | E20: 0 | F20: 0 | G20: 0 | H20: 0 | I20: 0 | J20: 0 | L20: 0 | M20: 0 | N20: 0 | O20: 0 | P20: 0 | Q20: 0
C21: 50.1 | D21: Natural Gas | E21: 0 | F21: 0 | G21: 0 | H21: 0 | I21: 0 | J21: 0 | L21: 0 | M21: 0 | N21: 0 | O21: 0 | P21: 0 | Q21: 0
C22: =C24+0.1 -> 50.9 | D22: Propane | E22: 0 | F22: 0 | G22: 0 | H22: 0 | I22: 0 | J22: 0 | L22: 0 | M22: 0 | N22: 0 | O22: 0 | P22: 0 | Q22: 0
C23: =C22+0.1 -> 51 | D23: Petroleum | E23: 0 | F23: 0 | G23: 0 | H23: 0 | I23: 0 | J23: 0 | L23: 0 | M23: 0 | N23: 0 | O23: 0 | P23: 0 | Q23: 0
C24: =C20+0.1 -> 50.8 | D24: Misc, Materials, Lumber, Poly | E24: 0 | F24: 0 | G24: 0 | H24: 0 | I24: 0 | J24: 0 | L24: 0 | M24: 0 | N24: 0 | O24: 0 | P24: 0 | Q24: 0
D25: Adjustment | E25: 0 | F25: 0 | G25: 0 | H25: 0 | I25: 0 | J25: 0 | L25: 0 | M25: 0 | N25: 0 | O25: 0 | P25: 0 | Q25: 0
E26: 0 | F26: 0 | G26: 0 | H26: 0 | I26: 0 | J26: 0 | L26: 0 | M26: 0 | N26: 0 | O26: 0 | P26: 0 | Q26: 0
D27: TOTALS | E27: =SUM(E12:E26) -> 0 | F27: =SUM(F12:F26) -> 0 | G27: =SUM(G12:G26) -> 0 | H27: =SUM(H12:H26) -> 0 | I27: =SUM(I12:I26) -> 0 | J27: =SUM(J12:J26) -> 0 | L27: =SUM(L12:L26) -> 0 | M27: =SUM(M12:M26) -> 0 | N27: =SUM(N12:N26) -> 0 | O27: =SUM(O12:O26) -> 0 | P27: =SUM(P12:P26) -> 0 | Q27: =SUM(Q12:Q26) -> 0
D31: Total Winter Conditions | F31: =SUM(E27:Q27) -> 0
D32: Allowance | F32: 0
D33: Net Change | F33: =F31-F32 -> 0

Sheet CLARIFICATIONS
C2: ='STEP 2 - GCs'!C2 -> E26-123.0
C3: ='STEP 2 - GCs'!C3 -> Project Name | D3: ='STEP 2 - GCs'!D3 -> Name
C4: ='STEP 2 - GCs'!C4 -> Location | D4: ='STEP 2 - GCs'!D4 -> 1234 Main St
D5: ='STEP 2 - GCs'!D5 -> Minneapolis, MN
C6: ='STEP 2 - GCs'!C6 -> Architect | D6: ='STEP 2 - GCs'!D6 -> TBD
C7: ='STEP 2 - GCs'!C7 -> Plan Set | D7: ='STEP 2 - GCs'!D7 -> TBD
C9: STANDARD CLARIFICATIONS AND EXCLUSIONS
C10: Handling or removal of hazardous materials.
C11: Builders Risk insurance policies.
C12: All bonds or any forms of security
C13: Special inspections and testing.
C14: Utility company charges of any kind. Any costs due to utility company requirements are not included.
C15: SAC / WAC fees or any governmental related fees other than the building permit.
C16: NPDES Permit.
C17: Soil corrections or buried debris / rubble.
C18: Design fees of any kind.
C19: Soil borings or geological reports.
C20: Miscellaneous site accessories including benches, bike racks, planters, and similar site elements.
... C35: PROJECT CLARIFICATIONS AND EXCLUSIONS

Sheet PER DIEM
M1: Low Risk
C2: ='STEP 1 - PROJECT DATA'!D6& "." & 'STEP 1 - PROJECT DATA'!D7 -> E26-123.0 | I2: ='STEP 4 - ESTIMATE'!I2 -> Bid Due Date | J2: ='STEP 4 - ESTIMATE'!K2 -> 46010 | M2: Medium Risk
C3: ='STEP 1 - PROJECT DATA'!C5 -> Project Name | D3: ='STEP 1 - PROJECT DATA'!D5 -> Name | E3: Per Diem | H3: ='STEP 1 - PROJECT DATA'!C10 -> Expected Start | J3: ='STEP 4 - ESTIMATE'!K3 -> 46174 | M3: High Risk
C4: Location | D4: ='STEP 1 - PROJECT DATA'!D8 -> 1234 Main St | H4: ='STEP 1 - PROJECT DATA'!C11 -> Expected Finish | J4: ='STEP 4 - ESTIMATE'!K4 -> 46235
D5: ='STEP 1 - PROJECT DATA'!D9 -> Minneapolis, MN | H5: Duration | J5: ='STEP 1 - PROJECT DATA'!D28 -> 2
C6: ='STEP 1 - PROJECT DATA'!C13 -> Architect | D6: ='STEP 1 - PROJECT DATA'!D13 -> TBD
C7: ='STEP 1 - PROJECT DATA'!C14 -> Plan Set | D7: ='STEP 1 - PROJECT DATA'!D14 -> TBD | J7: Bldg. Sqft.
J8: ='STEP 1 - PROJECT DATA'!D12 -> 10
C9: Code | D9: Description | E9: Utilization | F9: Quantity | G9: Unit | H9: Rate | I9: Total | J9: Cost/S.F.
C10: DIVISION 01 — SUPERVISION | D10: GENERAL CONDITIONS | E10: =SUM(I11:I15) -> 3464
C12: 01-0410 | D12: Sr Superintendent | E12: 1 | F12: =$J$5*4.33*40*E12 -> 346.4 | G12: hr | H12: 10 | I12: =F12*H12 -> 3464 | J12: =IF($J$8=0, 0, I12/$J$8) -> 346.4
C13: 01-0420 | D13: Superintendent | E13: 0 | F13: =$J$5*4.33*40*E13 -> 0 | G13: hr | H13: 10 | I13: =F13*H13 -> 0 | J13: =IF($J$8=0, 0, I13/$J$8) -> 0
C14: 01-0430 | D14: Asst. Superintendent | E14: 0 | F14: =$J$5*4.33*40*E14 -> 0 | G14: hr | H14: 10 | I14: =F14*H14 -> 0 | J14: =IF($J$8=0, 0, I14/$J$8) -> 0
C16: DIVISION 01 — PROJECT MANAGEMENT | D16: GENERAL CONDITIONS | E16: =SUM(I17:I23) -> 0
C18: 01-0310 | D18: Project Executive | E18: 0 | F18: =$J$5*4.33*40*E18 -> 0 | G18: hr | H18: 10 | I18: =F18*H18 -> 0 | J18: =IF($J$8=0, 0, I18/$J$8) -> 0
C19: 01-0320 | D19: Sr Project Manager | E19: 0 | F19: =$J$5*4.33*40*E19 -> 0 | G19: hr | H19: 10 | I19: =F19*H19 -> 0 | J19: =IF($J$8=0, 0, I19/$J$8) -> 0
C20: 01-0330 | D20: Project Manager | E20: 0 | F20: =$J$5*4.33*40*E20 -> 0 | G20: hr | H20: 10 | I20: =F20*H20 -> 0 | J20: =IF($J$8=0, 0, I20/$J$8) -> 0
C21: 01-0340 | D21: Project Engineer | E21: 0 | F21: =$J$5*4.33*40*E21 -> 0 | G21: hr | H21: 10 | I21: =F21*H21 -> 0 | J21: =IF($J$8=0, 0, I21/$J$8) -> 0
C22: 01-0510 | D22: Project Assistant | E22: 0 | F22: =$J$5*4.33*40*E22 -> 0 | G22: hr | H22: 10 | I22: =F22*H22 -> 0 | J22: =IF($J$8=0, 0, I22/$J$8) -> 0
C24: DIVISION 01 — FUEL AND VEHICLE CHARGES | D24: GENERAL CONDITIONS | E24: =SUM(I25:I35) -> 1701.69
C26: 01-1200 | D26: Fuel and Vehicle Charges
D27: Sr Superintendent | E27: 1 | F27: =$J$5*4.33*2*$D$60*E27 -> 2598 | G27: mi | H27: 0.655 | I27: =F27*H27 -> 1701.69 | J27: =IF($J$8=0, 0, I27/$J$8) -> 170.169
D28: Superintendent | E28: 0 | F28: =$J$5*4.33*2*$D$60*E28 -> 0 | G28: mi | H28: 0.655 | I28: =F28*H28 -> 0 | J28: =IF($J$8=0, 0, I28/$J$8) -> 0
D29: Asst. Superintendent | E29: 0 | F29: =$J$5*4.33*2*$D$60*E29 -> 0 | G29: mi | H29: 0.655 | I29: =F29*H29 -> 0 | J29: =IF($J$8=0, 0, I29/$J$8) -> 0
D30: Project Executive | E30: 0 | F30: =$J$5*4.33*2*$D$60*E30 -> 0 | G30: mi | H30: 0.655 | I30: =F30*H30 -> 0 | J30: =IF($J$8=0, 0, I30/$J$8) -> 0
D31: Sr Project Manager | E31: 0 | F31: =$J$5*4.33*2*$D$60*E31 -> 0 | G31: mi | H31: 0.655 | I31: =F31*H31 -> 0 | J31: =IF($J$8=0, 0, I31/$J$8) -> 0
D32: Project Manager | E32: 0 | F32: =$J$5*4.33*2*$D$60*E32 -> 0 | G32: mi | H32: 0.655 | I32: =F32*H32 -> 0 | J32: =IF($J$8=0, 0, I32/$J$8) -> 0
D33: Project Engineer | E33: 0 | F33: =$J$5*4.33*2*$D$60*E33 -> 0 | G33: mi | H33: 0.655 | I33: =F33*H33 -> 0 | J33: =IF($J$8=0, 0, I33/$J$8) -> 0
D34: Project Assistant | E34: 0 | F34: =$J$5*4.33*2*$D$60*E34 -> 0 | G34: mi | H34: 0.655 | I34: =F34*H34 -> 0 | J34: =IF($J$8=0, 0, I34/$J$8) -> 0
C36: DIVISION 01 — TRAVEL AND MEALS | D36: GENERAL CONDITIONS | E36: =SUM(I37:I47) -> 6495
C38: 01-1400 | D38: Travel and Meals
D39: Sr Superintendent | E39: 1 | F39: =$J$5*4.33*5*E39 -> 43.3 | G39: dy | H39: 150 | I39: =F39*H39 -> 6495 | J39: =IF($J$8=0, 0, I39/$J$8) -> 649.5
D40: Superintendent | E40: 0 | F40: =$J$5*4.33*5*E40 -> 0 | G40: dy | H40: 150 | I40: =F40*H40 -> 0 | J40: =IF($J$8=0, 0, I40/$J$8) -> 0
D41: Asst. Superintendent | E41: 0 | F41: =$J$5*4.33*5*E41 -> 0 | G41: dy | H41: 150 | I41: =F41*H41 -> 0 | J41: =IF($J$8=0, 0, I41/$J$8) -> 0
D42: Project Executive | E42: 0 | F42: =$J$5*4.33*5*E42 -> 0 | G42: dy | H42: 150 | I42: =F42*H42 -> 0 | J42: =IF($J$8=0, 0, I42/$J$8) -> 0
D43: Sr Project Manager | E43: 0 | F43: =$J$5*4.33*5*E43 -> 0 | G43: dy | H43: 150 | I43: =F43*H43 -> 0 | J43: =IF($J$8=0, 0, I43/$J$8) -> 0
D44: Project Manager | E44: 0 | F44: =$J$5*4.33*5*E44 -> 0 | G44: dy | H44: 150 | I44: =F44*H44 -> 0 | J44: =IF($J$8=0, 0, I44/$J$8) -> 0
D45: Project Engineer | E45: 0 | F45: =$J$5*4.33*5*E45 -> 0 | G45: dy | H45: 150 | I45: =F45*H45 -> 0 | J45: =IF($J$8=0, 0, I45/$J$8) -> 0
D46: Project Assistant | E46: 0 | F46: =$J$5*4.33*5*E46 -> 0 | G46: dy | H46: 150 | I46: =F46*H46 -> 0 | J46: =IF($J$8=0, 0, I46/$J$8) -> 0
H48: Total Per Diem | I48: =SUM(I11:I47) -> 11660.69 | J48: =IF($J$8=0, 0, I48/$J$8) -> 1166.069
C52: Project Information
C53: Project Name | D53: ='STEP 1 - PROJECT DATA'!D5 -> Name
C54: Estimate # | D54: ='STEP 1 - PROJECT DATA'!D6 -> E26-123
C55: Revision # | D55: ='STEP 1 - PROJECT DATA'!D7 -> 0
C56: Address | D56: ='STEP 1 - PROJECT DATA'!D8 -> 1234 Main St
C57: City, State, Zip | D57: ='STEP 1 - PROJECT DATA'!D9 -> Minneapolis, MN
C58: Expected Start | D58: ='STEP 1 - PROJECT DATA'!D10 -> 46174
C59: Expected Finish | D59: ='STEP 1 - PROJECT DATA'!D11 -> 46235
C60: Distance to Site | D60: 150 | E60: =HYPERLINK("https://www.google.com/maps/dir/" & SUBSTITUTE(D56, " ", "+") & "/" & SUBSTITUTE('STEP 1 - PROJECT DATA'!D21, " ", "+"), "Get Directions") -> Get Directions
C61: Per Diem | D61: =IF(D60>90, "Yes", "No") -> Yes
C62: Overnight Stay | D62: =IF(D60>90, "Yes", "No") -> Yes

Sheet TOWER CRANE
E1: Project Name:
E2: Location:
E3: Project Type:
E4: Date:
E5: Construction Duration:
D7: CRANE #1 | K7: CRANE #2
A9: Crane Duration | C9: 1 | D9: Months | H9: Crane Duration | J9: 1 | K9: Months
A10: Taxes | C10: 0.07125 | D10: Per Project Location | H10: Taxes | J10: 0.07125 | K10: Per Project Location
A12: ITEM DESCRIPTION | E12: Sub Name | H12: ITEM DESCRIPTION | L12: Sub Name
A14: Model | E14: Wolff WK325 | H14: Model | L14: Wolff WK325
A16: Hook Radius in feet | E16: 197 | H16: Hook Radius in feet | L16: 213
A18: Hook Height in feet | E18: 93 | H18: Hook Height in feet | L18: 197 or 211
A20: Crane Location (Grids) | E20: TBD | H20: Crane Location (Grids) | L20: TBD
A22: Erection and Dismantel Cost | E22: 64000 | H22: Erection and Dismantel Cost | L22: 139500
A24: Lease Rate per Month | D24: 13950 | H24: Lease Rate per Month | K24: 19950
A25: Months | D25: =$C$9 -> 1 | H25: Months | K25: =J9 -> 1
A26: Taxes | D26: =$C$10 -> 0.07125 | H26: Taxes | K26: =J10 -> 0.07125
A27: Total Lease Rate | E27: =(D24*D25)*(1+D26) -> 14943.938 | H27: Total Lease Rate | L27: =(K24*K25)*(1+K26) -> 21371.438
A29: Maintenance Rate per Month | D29: 700 | H29: Maintenance Rate per Month | K29: 700
A30: Months | D30: =$C$9 -> 1 | H30: Months | K30: =J9 -> 1
A31: Taxes | D31: =$C$10 -> 0.07125 | H31: Taxes | K31: =$C$10 -> 0.07125
A32: Total Maintenance Rate | E32: =(D29*D30)*(1+D31) -> 749.875 | H32: Total Maintenance Rate | L32: =(K29*K30)*(1+K31) -> 749.875
A34: Crane Base = poured concrete | E34: In Concrete | H34: Crane Base = poured concrete | L34: In Concrete
A36: Number of Piles | D36: 0 | H36: Number of Piles | K36: 0
A37: Cost Per Pile | D37: 1500 | H37: Cost Per Pile | K37: 1500
A38: Total Piling for the Crane Base | E38: =D37*D36 -> 0 | H38: Total Piling for the Crane Base | L38: =K37*K36 -> 0
A40: Electrical Hook-up | E40: In Electrical | H40: Electrical Hook-up | L40: In Electrical
A42: Electrical Power Usage | D42: 2000 | H42: Electrical Power Usage | K42: 2000
A43: Months | D43: =$C$9 -> 1 | H43: Months | K43: =J9 -> 1
A44: Total Electrical Power Usage | E44: =D43*D42 -> 2000 | H44: Total Electrical Power Usage | L44: =K43*K42 -> 2000
A46: Operator hrs/wk - Regular Rate | D46: 0 | H46: Operator hrs/wk - Regular Rate | K46: 0
A47: Operator Rate | D47: 82.92 | H47: Operator Rate | K47: 82.92
A48: Months | D48: =$C$9 -> 1 | H48: Months | K48: =J9 -> 1
A49: Operator Total - Regular Rate | E49: =(D48*4.33)*D47*D46 -> 0 | H49: Operator Total - Regular Rate | L49: =(K48*4.33)*K47*K46 -> 0
A51: Operator hrs/wk - Overtime | D51: 0 | H51: Operator hrs/wk - Overtime | K51: 0
A52: Operator Rate | D52: 110.93 | H52: Operator Rate | K52: 110.93
A53: Months | D53: =$C$9 -> 1 | H53: Months | K53: =J9 -> 1
A54: Operator Total - Overtime | E54: =(D53*4.33)*D52*D51 -> 0 | H54: Operator Total - Overtime | L54: =(K53*4.33)*K52*K51 -> 0
A56: Permits - Allowance | E56: 10000 | H56: Permits - Allowance | L56: 10000
A58: Signage | E58: 0 | H58: Signage | L58: 0
A60: TOTAL COST FOR THE TOWER CRANE | E60: =SUM(E22:E59) -> 91693.812 | H60: TOTAL COST FOR THE TOWER CRANE | L60: =SUM(L22:L59) -> 173621.31
A62: Cost in the Estimate | E62: 507984 | H62: Cost in the Estimate | L62: 846640
A63: Difference | E63: =E60-E62 -> -416290.19 | H63: Difference | L63: =L60-L62 -> -673018.69
A65: Per Month Cost | E65: =E60/C9 -> 91693.812 | H65: Per Month Cost | L65: =L60/J9 -> 173621.31

Sheet SKIP
E1: Project Name:
E2: Location:
E3: Project Type:
E4: Date:
E5: Construction Duration:
A7: Man/Material Hoist - Single Car | H7: Man/Material Hoist - Double Car
A9: Hoist Duration | C9: 0 | D9: Months | H9: Hoist Duration | J9: 15 | K9: Months
A10: Hoist Levels | C10: 0 | D10: Levels | H10: Hoist Levels | J10: 26 | K10: Levels
A11: Taxes | C11: 0.07125 | D11: Per Project Location | H11: Taxes | J11: 0.07125 | K11: Per Project Location
A13: ITEM DESCRIPTION | E13: Sub Name | H13: ITEM DESCRIPTION | L13: Sub Name
A15: Model | E15: Single Car | H15: Model | L15: Double Car
A17: Capacity | E17: 6000# | H17: Capacity | L17: 6000#
A19: Car Size | E19: 4'-8"x12'-4"x7'-6" | H19: Car Size | L19: 4'-8"x12'-4"x7'-2"
A21: Speed | E21: 150 ft/mn | H21: Speed | L21: 300 ft/mn
A23: Erection and Dismantel Cost | E23: 24250 | H23: Erection and Dismantel Cost | L23: 58000
A25: Lease Rate per Month | D25: 5500 | H25: Lease Rate per Month | K25: =15500+750 -> 16250
A26: Months | D26: =C9 -> 0 | H26: Months | K26: =J9 -> 15
A27: Taxes | D27: =C11 -> 0.07125 | H27: Taxes | K27: =J11 -> 0.07125
A28: Total Lease Rate | E28: =(D25*D26)*(1+D27) -> 0 | H28: Total Lease Rate | L28: =(K25*K26)*(1+K27) -> 261117.19
A30: Quarterly Inspections | D30: =C9/3 -> 0 | H30: Quarterly Inspections | K30: =J9/3 -> 5
A31: Quarterly Inspections Costs | D31: 1000 | H31: Quarterly Inspections Costs | K31: =130*2*6 -> 1560
A32: Total Quarterly Inspections | E32: =D31*D30 -> 0 | H32: Total Quarterly Inspections | L32: =K31*K30 -> 7800
A34: Maintenance Costs/Month | D34: 650 | H34: Maintenance Costs/Month | K34: 650
A35: Maintenance Months | D35: =C9 -> 0 | H35: Maintenance Months | K35: =J9 -> 15
A36: Maintenance Costs | E36: =D35*D34 -> 0 | H36: Maintenance Costs | L36: =K35*K34 -> 9750
A38: Number of Landing Gates | D38: =C10 -> 0 | H38: Number of Landing Gates | K38: =J10 -> 26
A39: Monthly Rental | D39: 155 | H39: Monthly Rental | K39: 155
A40: Months | D40: =C9 -> 0 | H40: Months | K40: =J9 -> 15
A41: Total Gates Costs | E41: =D40*D39*D38 -> 0 | H41: Total Gates Costs | L41: =K40*K39*K38 -> 60450
A43: Slab Extensions | E43: confirm | H43: Slab Extensions | L43: confirm
A45: Call System Rate | D45: 650 | H45: Call System Rate | K45: 1350
A46: Months | D46: =C9 -> 0 | H46: Months | K46: =J9 -> 15
A47: Total Call System | E47: =D46*D45 -> 0 | H47: Total Call System | L47: =K46*K45 -> 20250
A49: Hoist Base = poured concrete | E49: In Concrete | H49: Hoist Base = poured concrete | L49: In Concrete
A51: Number of Piles | D51: 0 | H51: Number of Piles | K51: 0
A52: Cost Per Pile | D52: 1500 | H52: Cost Per Pile | K52: 1500
A53: Total Piling for the Crane Base | E53: =D52*D51 -> 0 | H53: Total Piling for the Crane Base | L53: =K52*K51 -> 0
A55: Electrical Hook-up | E55: Included in Electrical | H55: Electrical Hook-up | L55: Included in Electrical
A57: Electrical Power Usage | D57: 1500 | H57: Electrical Power Usage | K57: 1500
A58: Months | D58: =C9 -> 0 | H58: Months | K58: =J9 -> 15
A59: Total Electrical Power Usage | E59: =D58*D57 -> 0 | H59: Total Electrical Power Usage | L59: =K58*K57 -> 22500
A61: Operator hrs/wk - Regular Rate | D61: 40 | H61: Operator hrs/wk - Regular Rate | K61: 40
A62: Operator Rate | D62: 85.5 | H62: Operator Rate | K62: 85.5
A63: Months | D63: =C9 -> 0 | H63: Months | K63: 20
A64: Operator Total - Regular Rate | E64: =(D61*4.33)*D62*D63 -> 0 | H64: Operator Total - Regular Rate | L64: 100000
A66: Operator hrs/wk - Overtime | D66: 5 | H66: Operator hrs/wk - Overtime | K66: 5
A67: Operator Rate | D67: 113.42 | H67: Operator Rate | K67: 113.42
A68: Months | D68: =C9 -> 0 | H68: Months | K68: =J9 -> 15
A69: Operator Total - Overtime | E69: =(D68*4.33)*D67*D66 -> 0 | H69: Operator Total - Overtime
A71: Special Engineering for Reaction Forces | E71: 500 | H71: Special Engineering for Reaction Forces | L71: 500
A73: Permits - Allowance | E73: 5000 | H73: Permits - Allowance | L73: 5000
A75: TOTAL COST FOR THE MAN/MATERIAL HOIST | E75: =SUM(E23:E74) -> 29750 | H75: TOTAL COST FOR THE MAN/MATERIAL HOIST | L75: =SUM(L23:L74) -> 545367.19
A77: Cost in the Estimate | E77: 0 | H77: Cost in the Estimate | L77: 0
A78: Difference | E78: =E75-E77 -> 29750 | H78: Difference | L78: =L75-L77 -> 545367.19
A80: Per Month Cost | E80: =E75/C9 -> #DIV/0! | H80: Per Month Cost | L80: =L75/J9 -> 36357.812
L83: =L75/12 -> 45447.266

Sheet STREET CLOSURES
E1: Project Name:
E2: Location: | I2: https://www2.minneapolismn.gov/business-services/licenses-permits-inspections/streets-sidewalks-utility/city-lane-use-permits/lane-use-fee-changes/
E3: Project Type:
E4: Date:
E5: Construction Duration:
A7: Street Closures
A9: North Street Name: | G9: South Street Name:
A10: North Street Duration: | B10: 2 | C10: Months | G10: South Street Duration: | H10: 18 | I10: Months
A12: Type | B12: Months | C12: Length/Each | D12: $/FT-EA/Day | E12: Total | G12: Type | H12: Months | I12: Length/Each | J12: $/FT-EA/Day | K12: Total
A13: Moving Lane | B13: =B10 -> 2 | C13: 341 | D13: 0.5 | E13: =(B13*4.33*7)*C13*D13 -> 10335.71 | G13: Moving Lane | H13: =H10 -> 18 | I13: 0 | J13: 0.5 | K13: =(H13*4.33*7)*I13*J13 -> 0
A14: Parking | B14: =B10 -> 2 | C14: 0 | D14: 0.15 | E14: =(B14*4.33*7)*C14*D14 -> 0 | G14: Parking | H14: =H10 -> 18 | I14: 388 | J14: 0.15 | K14: =(H14*4.33*7)*I14*J14 -> 31752.756
A15: Sidewalk | B15: =B10 -> 2 | C15: 0 | D15: 0.15 | E15: =(B15*4.33*7)*C15*D15 -> 0 | G15: Sidewalk | H15: =H10 -> 18 | I15: 388 | J15: 0.15 | K15: =(H15*4.33*7)*I15*J15 -> 31752.756
A16: Bike Lane | B16: =B10 -> 2 | C16: 341 | D16: 0.15 | E16: =(B16*4.33*7)*C16*D16 -> 3100.713 | G16: Bike Lane | H16: =H10 -> 18 | I16: 0 | J16: 0.15 | K16: =(H16*4.33*7)*I16*J16 -> 0
A17: Alley | B17: =B10 -> 2 | C17: 0 | D17: 0.15 | E17: =(B17*4.33*7)*C17*D17 -> 0 | G17: Alley | H17: =H10 -> 18 | I17: 0 | J17: 0.15 | K17: =(H17*4.33*7)*I17*J17 -> 0
A18: Parking Meters | B18: =B10 -> 2 | C18: 0 | D18: 7.36 | E18: =(B18*4.33*7)*C18*D18 -> 0 | G18: Parking Meters | H18: =H10 -> 18 | I18: 13 | J18: 7.36 | K18: =(H18*4.33*7)*I18*J18 -> 52201.094
A19: Parking Meters Remove and Install Pipe | C19: 0 | D19: 100 | E19: =D19*C19 -> 0 | G19: Parking Meters Remove and Install Pipe | I19: 7 | J19: 100 | K19: =J19*I19 -> 700
A20: Subtotal North Street | E20: =SUM(E13:E19) -> 13436.423 | G20: Subtotal South Street | K20: =SUM(K13:K19) -> 116406.61
A22: West Street Name: | G22: East Street Name:
A23: West Street Duration: | B23: 20 | C23: Months | G23: East Street Duration: | H23: 24 | I23: Months
A25: Type | B25: Months | C25: Length/Each | D25: $/FT-EA/Day | E25: Total | G25: Type | H25: Months | I25: Length/Each | J25: $/FT-EA/Day | K25: Total
A26: Moving Lane | B26: =B23 -> 20 | C26: 0 | D26: 0.5 | E26: =(B26*4.33*7)*C26*D26 -> 0 | G26: Moving Lane | H26: =H23 -> 24 | I26: 0 | J26: 0.5 | K26: =(H26*4.33*7)*I26*J26 -> 0
A27: Parking | B27: =B23 -> 20 | C27: 0 | D27: 0.15 | E27: =(B27*4.33*7)*C27*D27 -> 0 | G27: Parking | H27: =H23 -> 24 | I27: 0 | J27: 0.15 | K27: =(H27*4.33*7)*I27*J27 -> 0
A28: Sidewalk | B28: =B23 -> 20 | C28: 0 | D28: 0.15 | E28: =(B28*4.33*7)*C28*D28 -> 0 | G28: Sidewalk | H28: =H23 -> 24 | I28: 0 | J28: 0.15 | K28: =(H28*4.33*7)*I28*J28 -> 0
A29: Bike Lane | B29: =B23 -> 20 | C29: 0 | D29: 0.15 | E29: =(B29*4.33*7)*C29*D29 -> 0 | G29: Bike Lane | H29: =H23 -> 24 | I29: 0 | J29: 0.15 | K29: =(H29*4.33*7)*I29*J29 -> 0
A30: Alley | B30: =B23 -> 20 | C30: 0 | D30: 0.15 | E30: =(B30*4.33*7)*C30*D30 -> 0 | G30: Alley | H30: =H23 -> 24 | I30: 0 | J30: 0.15 | K30: =(H30*4.33*7)*I30*J30 -> 0
A31: Parking Meters | B31: =B23 -> 20 | C31: 12 | D31: 7.36 | E31: =(B31*4.33*7)*C31*D31 -> 53539.584 | G31: Parking Meters | H31: =H23 -> 24 | I31: 23 | J31: 7.36 | K31: =(H31*4.33*7)*I31*J31 -> 123141.04
A32: Parking Meters Remove and Install Pipe | C32: 6 | D32: 100 | E32: =D32*C32 -> 600 | G32: Parking Meters Remove and Install Pipe | I32: 13 | J32: 100 | K32: =J32*I32 -> 1300
A33: Subtotal West Street | E33: =SUM(E26:E32) -> 54139.584 | G33: Subtotal East Street | K33: =SUM(K26:K32) -> 124441.04
A36: Grand Total | E36: =E20+E33+K20+K33 -> 308423.66
A38: Per Month- Based on the Total Project Duration | E38: =E36/G5 -> #DIV/0!
A41: Parking Meter Total | E41: =E32+E31+K19+K18+K32+K31 -> 231481.72
A42: Street Closures | E42: =E36-E41 -> 76941.935
A44: Previous Estimate | E44: 288000
A45: Difference | E45: =E36-E44 -> 20423.657

Sheet STORM RETENTION
A2: Building Permit Calculation
A4: Impervious Area (SF) | B4: 20000
A5: Rainfall (inches) | B5: 1
A6: Runoff Coefficient | B6: 0.9
A7: Conversion factor | B7: 0.623
A9: Storage Volume (Gallons) | C9: =B4*B5*B6*B7 -> 11214

Sheet Budget Line Items
A1: Cost Code | B1: Cost Type | C1: Description | D1: Manual Calculation | E1: Unit Qty | F1: UOM | G1: Unit Cost | H1: Budget Amount | I1: Start Date | J1: End Date | K1: Curve
A2: 1-10000.000 | B2: Material | C2: General Conditions | E2: 1 | F2: ls | H2: =SUMIF('STEP 2 - GCs'!$C$2:$C$603, 'STEP 2 - GCs'!#REF!, 'STEP 2 - GCs'!$I$2:$I$603) -> 0
A3: 1-10001.000 | B3: Material | C3: Preconstruction Fees | E3: 1 | F3: ls | H3: =SUMIF('STEP 2 - GCs'!$C$2:$C$603, 'STEP 2 - GCs'!C19, 'STEP 2 - GCs'!$I$2:$I$603) -> 0
A4: 1-10130.000 | B4: Material | C4: Design - Architecture | E4: 1 | F4: ls | H4: =SUMIF('STEP 2 - GCs'!$C$2:$C$603, 'STEP 2 - GCs'!C20, 'STEP 2 - GCs'!$I$2:$I$603) -> 0
A5: 1-10160.000 | B5: Material | C5: Design - Civil | E5: 1 | F5: ls | H5: =SUMIF('STEP 2 - GCs'!$C$2:$C$603, 'STEP 2 - GCs'!C21, 'STEP 2 - GCs'!$I$2:$I$603) -> 0
A6: 1-10180.000 | B6: Material | C6: Design - MEP | E6: 1 | F6: ls | H6: =SUMIF('STEP 2 - GCs'!$C$2:$C$603, 'STEP 2 - GCs'!C22, 'STEP 2 - GCs'!$I$2:$I$603) -> 0
A7: 1-10210.000 | B7: Material | C7: Design - Structural | E7: 1 | F7: ls | H7: =SUMIF('STEP 2 - GCs'!$C$2:$C$603, 'STEP 2 - GCs'!C23, 'STEP 2 - GCs'!$I$2:$I$603) -> 0
A8: 1-10230.000 | B8: Material | C8: Building Permit | E8: 1 | F8: ls | H8: =SUMIF('STEP 4 - ESTIMATE'!$C$2:$C$630, 'STEP 4 - ESTIMATE'!C327, 'STEP 4 - ESTIMATE'!$I$2:$I$630) -> 2742.531
A9: 1-10250.000 | B9: Material | C9: Demolition Permit | E9: 1 | F9: ls | H9: =SUMIF('STEP 4 - ESTIMATE'!$C$2:$C$630, 'STEP 4 - ESTIMATE'!C328, 'STEP 4 - ESTIMATE'!$I$2:$I$630) -> 0
A10: 1-10260.000 | B10: Material | C10: City Licenses/Misc Permits | E10: 1 | F10: ls | H10: =SUMIF('STEP 4 - ESTIMATE'!$C$2:$C$630, 'STEP 4 - ESTIMATE'!C329, 'STEP 4 - ESTIMATE'!$I$2:$I$630) -> 0
A11: 1-10310.000 | B11: Labor | C11: Project Executive | E11: 1 | F11: ls | H11: =SUMIF('STEP 2 - GCs'!$C$2:$C$603, 'STEP 2 - GCs'!C27, 'STEP 2 - GCs'!$I$2:$I$603) -> 0
A12: 1-10320.000 | B12: Labor | C12: Sr Project Manager | E12: 1 | F12: ls | H12: =SUMIF('STEP 2 - GCs'!$C$2:$C$603, 'STEP 2 - GCs'!C28, 'STEP 2 - GCs'!$I$2:$I$603) -> 23382
A13: 1-10330.000 | B13: Labor | C13: Project Manager | E13: 1 | F13: ls | H13: =SUMIF('STEP 2 - GCs'!$C$2:$C$603, 'STEP 2 - GCs'!C29, 'STEP 2 - GCs'!$I$2:$I$603) -> 0
A14: 1-10340.000 | B14: Labor | C14: Project Engineer | E14: 1 | F14: ls | H14: =SUMIF('STEP 2 - GCs'!$C$2:$C$603, 'STEP 2 - GCs'!C30, 'STEP 2 - GCs'!$I$2:$I$603) -> 0
A15: 1-10410.000 | B15: Labor | C15: Sr Superintendent | E15: 1 | F15: ls | H15: =SUMIF('STEP 2 - GCs'!$C$2:$C$603, 'STEP 2 - GCs'!C12, 'STEP 2 - GCs'!$I$2:$I$603) -> 43300
A16: 1-10420.000 | B16: Labor | C16: Superintendent | E16: 1 | F16: ls | H16: =SUMIF('STEP 2 - GCs'!$C$2:$C$603, 'STEP 2 - GCs'!C13, 'STEP 2 - GCs'!$I$2:$I$603) -> 0
A17: 1-10430.000 | B17: Labor | C17: Asst. Superintendent | E17: 1 | F17: ls | H17: =SUMIF('STEP 2 - GCs'!$C$2:$C$603, 'STEP 2 - GCs'!C14, 'STEP 2 - GCs'!$I$2:$I$603) -> 0
A18: 1-10510.000 | B18: Labor | C18: Project Assistant | E18: 1 | F18: ls | H18: =SUMIF('STEP 2 - GCs'!$C$2:$C$603, 'STEP 2 - GCs'!C31, 'STEP 2 - GCs'!$I$2:$I$603) -> 0
A19: 1-10610.000 | B19: Material | C19: Safety Consultant, Visit Bi-Weekly | E19: 1 | F19: ls | H19: =SUMIF('STEP 2 - GCs'!$C$2:$C$603, 'STEP 2 - GCs'!C35, 'STEP 2 - GCs'!$I$2:$I$603) -> 23.4778
A20: 1-11000.000 | B20: Material | C20: Small Tools | E20: 1 | F20: ls | H20: =SUMIF('STEP 2 - GCs'!$C$2:$C$603, 'STEP 2 - GCs'!C36, 'STEP 2 - GCs'!$I$2:$I$603) -> 1000
A21: 1-11200.000 | B21: Material | C21: Fuel and Vehicle Charges | E21: 1 | F21: ls | H21: =SUMIF('STEP 2 - GCs'!$C$2:$C$603, 'STEP 2 - GCs'!C37, 'STEP 2 - GCs'!$I$2:$I$603) -> 2400
A22: 1-11400.000 | B22: Material | C22: Travel and Meals | E22: 1 | F22: ls | H22: =SUMIF('STEP 2 - GCs'!$C$2:$C$603, 'STEP 2 - GCs'!C38, 'STEP 2 - GCs'!$I$2:$I$603) -> 0
A23: 1-11600.000 | B23: Material | C23: Procore | E23: 1 | F23: ls | H23: =SUMIF('STEP 2 - GCs'!$C$2:$C$603, 'STEP 2 - GCs'!C39, 'STEP 2 - GCs'!$I$2:$I$603) -> 223.0391
A24: 1-14010.000 | B24: Material | C24: Quality | E24: 1 | F24: ls | H24: =SUMIF('STEP 2 - GCs'!$C$2:$C$603, 'STEP 2 - GCs'!C40, 'STEP 2 - GCs'!$I$2:$I$603) -> 1000
A25: 1-15110.000 | B25: Material | C25: Temp Office and Set up | E25: 1 | F25: ls | H25: =SUMIF('STEP 2 - GCs'!$C$2:$C$603, 'STEP 2 - GCs'!C41, 'STEP 2 - GCs'!$I$2:$I$603) -> 10700
A26: 1-15111.000 | B26: Material | C26: Cell Phone | E26: 1 | F26: ls | H26: =SUMIF('STEP 2 - GCs'!$C$2:$C$603, 'STEP 2 - GCs'!C43, 'STEP 2 - GCs'!$I$2:$I$603) -> 270
A27: 1-15112.000 | B27: Material | C27: Jobsite Office Equipment | E27: 1 | F27: ls | H27: =SUMIF('STEP 2 - GCs'!$C$2:$C$603, 'STEP 2 - GCs'!C44, 'STEP 2 - GCs'!$I$2:$I$603) -> 500
A28: 1-15114.000 | B28: Material | C28: Project Computers / Internet | E28: 1 | F28: ls | H28: =SUMIF('STEP 2 - GCs'!$C$2:$C$603, 'STEP 2 - GCs'!C45, 'STEP 2 - GCs'!$I$2:$I$603) -> 600
A29: 1-15120.000 | B29: Material | C29: Storage Trailer | E29: 1 | F29: ls | H29: =SUMIF('STEP 2 - GCs'!$C$2:$C$603, 'STEP 2 - GCs'!C46, 'STEP 2 - GCs'!$I$2:$I$603) -> 1600
A30: 1-15130.000 | B30: Material | C30: Dumpsters | E30: 1 | F30: ls | H30: =SUMIF('STEP 2 - GCs'!$C$2:$C$603, 'STEP 2 - GCs'!C47, 'STEP 2 - GCs'!$I$2:$I$603) -> 5200
A31: 1-15140.000 | B31: Material | C31: Temporary Toilets | E31: 1 | F31: ls | H31: =SUMIF('STEP 2 - GCs'!$C$2:$C$603, 'STEP 2 - GCs'!C48, 'STEP 2 - GCs'!$I$2:$I$603) -> 2000
A32: 1-15150.000 | B32: Material | C32: Temporary Fire Extinguishers | E32: 1 | F32: ls | H32: =SUMIF('STEP 2 - GCs'!$C$2:$C$603, 'STEP 2 - GCs'!C49, 'STEP 2 - GCs'!$I$2:$I$603) -> 0.33333333
A33: 1-15160.000 | B33: Material | C33: Temporary Project Signs | E33: 1 | F33: ls | H33: =SUMIF('STEP 2 - GCs'!$C$2:$C$603, 'STEP 2 - GCs'!C50, 'STEP 2 - GCs'!$I$2:$I$603) -> 1500
A34: 1-15170.000 | B34: Material | C34: Temporary Electric | E34: 1 | F34: ls | H34: =SUMIF('STEP 2 - GCs'!$C$2:$C$603, 'STEP 2 - GCs'!C51, 'STEP 2 - GCs'!$I$2:$I$603) -> 5000
A35: 1-15180.000 | B35: Material | C35: Temporary Gas (not winter heat) | E35: 1 | F35: ls | H35: =SUMIF('STEP 2 - GCs'!$C$2:$C$603, 'STEP 2 - GCs'!C52, 'STEP 2 - GCs'!$I$2:$I$603) -> 1800
A36: 1-15190.000 | B36: Material | C36: Temporary Water | E36: 1 | F36: ls | H36: =SUMIF('STEP 2 - GCs'!$C$2:$C$603, 'STEP 2 - GCs'!C53, 'STEP 2 - GCs'!$I$2:$I$603) -> 1300
A37: 1-16010.000 | B37: Material | C37: Courier services | E37: 1 | F37: ls | H37: =SUMIF('STEP 2 - GCs'!$C$2:$C$603, 'STEP 2 - GCs'!C54, 'STEP 2 - GCs'!$I$2:$I$603) -> 700
... A39: 1-17010.000 | B39: Material | C39: Legal Fees | E39: 1 | F39: ls | H39: =SUMIF('STEP 2 - GCs'!$C$2:$C$603, 'STEP 2 - GCs'!C56, 'STEP 2 - GCs'!$I$2:$I$603) -> 5000
A40: 2-23200.000 | B40: Material | C40: Soil Borings | E40: 1 | F40: ls | H40: =SUMIF('STEP 3 - SITE OPS'!$C$2:$C$608, 'STEP 3 - SITE OPS'!C12, 'STEP 3 - SITE OPS'!$I$2:$I$608) -> 0
A41: 2-24100.000 | B41: Subcontract | C41: Demolition | E41: 1 | F41: ls | H41: =SUMIF('STEP 3 - SITE OPS'!$C$2:$C$608, 'STEP 3 - SITE OPS'!C32, 'STEP 3 - SITE OPS'!$I$2:$I$608) -> 0
A42: 2-25100.000 | B42: Subcontract | C42: FFE Relocation | E42: 1 | F42: ls | H42: =SUMIF('STEP 3 - SITE OPS'!$C$2:$C$608, 'STEP 3 - SITE OPS'!C13, 'STEP 3 - SITE OPS'!$I$2:$I$608) -> 0
A43: 2-28213.000 | B43: Subcontract | C43: Abatement | E43: 1 | F43: ls | H43: =SUMIF('STEP 3 - SITE OPS'!$C$2:$C$608, 'STEP 3 - SITE OPS'!C14, 'STEP 3 - SITE OPS'!$I$2:$I$608) -> 0
A44: 2-29005.000 | B44: Subcontract | C44: Final Cleaning | E44: 1 | F44: ls | H44: =SUMIF('STEP 3 - SITE OPS'!$C$2:$C$608, 'STEP 3 - SITE OPS'!C38, 'STEP 3 - SITE OPS'!$I$2:$I$608) -> 0
A45: 2-29010.000 | B45: Material | C45: Progress Cleaning | E45: 1 | F45: ls | H45: =SUMIF('STEP 3 - SITE OPS'!$C$2:$C$608, 'STEP 3 - SITE OPS'!C15, 'STEP 3 - SITE OPS'!$I$2:$I$608) -> 0
A46: 2-29015.000 | B46: Material | C46: Safety | E46: 1 | F46: ls | H46: =SUMIF('STEP 3 - SITE OPS'!$C$2:$C$608, 'STEP 3 - SITE OPS'!C17, 'STEP 3 - SITE OPS'!$I$2:$I$608) -> 0
A47: 2-29020.000 | B47: Material | C47: Temp Protection | E47: 1 | F47: ls | H47: =SUMIF('STEP 3 - SITE OPS'!$C$2:$C$608, 'STEP 3 - SITE OPS'!C18, 'STEP 3 - SITE OPS'!$I$2:$I$608) -> 2.5
A48: 2-29025.000 | B48: Material | C48: Temporary Partitions | E48: 1 | F48: ls | H48: =SUMIF('STEP 3 - SITE OPS'!$C$2:$C$608, 'STEP 3 - SITE OPS'!C19, 'STEP 3 - SITE OPS'!$I$2:$I$608) -> 0
A49: 2-29030.000 | B49: Material | C49: Traffic Control and Jersey Barriers | E49: 1 | F49: ls | H49: =SUMIF('STEP 3 - SITE OPS'!$C$2:$C$608, 'STEP 3 - SITE OPS'!C20, 'STEP 3 - SITE OPS'!$I$2:$I$608) -> 0
A50: 2-29035.000 | B50: Material | C50: Temporary Fencing | E50: 1 | F50: ls | H50: =SUMIF('STEP 3 - SITE OPS'!$C$2:$C$608, 'STEP 3 - SITE OPS'!C21, 'STEP 3 - SITE OPS'!$I$2:$I$608) -> 0
A51: 2-29040.000 | B51: Material | C51: Scrim | E51: 1 | F51: ls | H51: =SUMIF('STEP 3 - SITE OPS'!$C$2:$C$608, 'STEP 3 - SITE OPS'!C22, 'STEP 3 - SITE OPS'!$I$2:$I$608) -> 0
A52: 2-29045.000 | B52: Subcontract | C52: Temp Access Roads | E52: 1 | F52: ls | H52: =SUMIF('STEP 3 - SITE OPS'!$C$2:$C$608, 'STEP 3 - SITE OPS'!C23, 'STEP 3 - SITE OPS'!$I$2:$I$608) -> 0
A53: 2-29050.000 | B53: Material | C53: Site Security | E53: 1 | F53: ls | H53: =SUMIF('STEP 3 - SITE OPS'!$C$2:$C$608, 'STEP 3 - SITE OPS'!C24, 'STEP 3 - SITE OPS'!$I$2:$I$608) -> 0
A54: 2-29055.000 | B54: Material | C54: Site Security Cameras | E54: 1 | F54: ls | H54: =SUMIF('STEP 3 - SITE OPS'!$C$2:$C$608, 'STEP 3 - SITE OPS'!C25, 'STEP 3 - SITE OPS'!$I$2:$I$608) -> 0
A55: 2-29060.000 | B55: Material | C55: Jobsite Camera | E55: 1 | F55: ls | H55: =SUMIF('STEP 3 - SITE OPS'!$C$2:$C$608, 'STEP 3 - SITE OPS'!C26, 'STEP 3 - SITE OPS'!$I$2:$I$608) -> 0
A56: 2-29065.000 | B56: Material | C56: Construction Permits | E56: 1 | F56: ls | H56: =SUMIF('STEP 3 - SITE OPS'!$C$2:$C$608, 'STEP 3 - SITE OPS'!C27, 'STEP 3 - SITE OPS'!$I$2:$I$608) -> 0
A57: 2-29070.000 | B57: Material | C57: SWPPP Permit | E57: 1 | F57: ls | H57: =SUMIF('STEP 3 - SITE OPS'!$C$2:$C$608, 'STEP 3 - SITE OPS'!C43, 'STEP 3 - SITE OPS'!$I$2:$I$608) -> 0
A58: 2-29200.000 | B58: Subcontract | C58: Survey & Layout | E58: 1 | F58: ls | H58: =SUMIF('STEP 3 - SITE OPS'!$C$2:$C$608, 'STEP 3 - SITE OPS'!C48, 'STEP 3 - SITE OPS'!$I$2:$I$608) -> 0
A59: 2-29305.000 | B59: Material | C59: City Requirements | E59: 1 | F59: ls | H59: =SUMIF('STEP 3 - SITE OPS'!$C$2:$C$608, 'STEP 3 - SITE OPS'!C54, 'STEP 3 - SITE OPS'!$I$2:$I$608) -> 0
A60: 2-29307.000 | B60: Material | C60: Knox Box | E60: 1 | F60: ls | H60: =SUMIF('STEP 3 - SITE OPS'!$C$2:$C$608, 'STEP 3 - SITE OPS'!C55, 'STEP 3 - SITE OPS'!$I$2:$I$608) -> 0
A61: 2-29310.000 | B61: Material | C61: Permanent Power Service | E61: 1 | F61: ls | H61: =SUMIF('STEP 3 - SITE OPS'!$C$2:$C$608, 'STEP 3 - SITE OPS'!C56, 'STEP 3 - SITE OPS'!$I$2:$I$608) -> 0
A62: 2-29315.000 | B62: Material | C62: Temporary Power Service | E62: 1 | F62: ls | H62: =SUMIF('STEP 3 - SITE OPS'!$C$2:$C$608, 'STEP 3 - SITE OPS'!C57, 'STEP 3 - SITE OPS'!$I$2:$I$608) -> 0
A63: 2-29320.000 | B63: Material | C63: Gas Service | E63: 1 | F63: ls | H63: =SUMIF('STEP 3 - SITE OPS'!$C$2:$C$608, 'STEP 3 - SITE OPS'!C58, 'STEP 3 - SITE OPS'!$I$2:$I$608) -> 0
A64: 2-29325.000 | B64: Material | C64: Cable Service | E64: 1 | F64: ls | H64: =SUMIF('STEP 3 - SITE OPS'!$C$2:$C$608, 'STEP 3 - SITE OPS'!C59, 'STEP 3 - SITE OPS'!$I$2:$I$608) -> 0
A65: 2-29330.000 | B65: Material | C65: Data Service | E65: 1 | F65: ls | H65: =SUMIF('STEP 3 - SITE OPS'!$C$2:$C$608, 'STEP 3 - SITE OPS'!C60, 'STEP 3 - SITE OPS'!$I$2:$I$608) -> 0
A66: 2-29405.000 | B66: Material | C66: Material Hoist / Trash Chute | E66: 1 | F66: ls | H66: =SUMIF('STEP 3 - SITE OPS'!$C$2:$C$608, 'STEP 3 - SITE OPS'!C65, 'STEP 3 - SITE OPS'!$I$2:$I$608) -> 0
A67: 2-29410.000 | B67: Material | C67: Scaffolding & Platforms | E67: 1 | F67: ls | H67: =SUMIF('STEP 3 - SITE OPS'!$C$2:$C$608, 'STEP 3 - SITE OPS'!C66, 'STEP 3 - SITE OPS'!$I$2:$I$608) -> 0
A68: 2-29415.000 | B68: Material | C68: Crane Rental | E68: 1 | F68: ls | H68: =SUMIF('STEP 3 - SITE OPS'!$C$2:$C$608, 'STEP 3 - SITE OPS'!C67, 'STEP 3 - SITE OPS'!$I$2:$I$608) -> 0
A69: 2-29420.000 | B69: Material | C69: Equipment Rental | E69: 1 | F69: ls | H69: =SUMIF('STEP 3 - SITE OPS'!$C$2:$C$608, 'STEP 3 - SITE OPS'!C68, 'STEP 3 - SITE OPS'!$I$2:$I$608) -> 0
A70: 2-29425.000 | B70: Material | C70: Forklift Rental | E70: 1 | F70: ls | H70: =SUMIF('STEP 3 - SITE OPS'!$C$2:$C$608, 'STEP 3 - SITE OPS'!C69, 'STEP 3 - SITE OPS'!$I$2:$I$608) -> 0
A71: 2-29430.000 | B71: Material | C71: Street Sweeping | E71: 1 | F71: ls | H71: =SUMIF('STEP 3 - SITE OPS'!$C$2:$C$608, 'STEP 3 - SITE OPS'!C70, 'STEP 3 - SITE OPS'!$I$2:$I$608) -> 0
A72: 2-29505.000 | B72: Material | C72: Const Materials Testing | E72: 1 | F72: ls | H72: =SUMIF('STEP 3 - SITE OPS'!$C$2:$C$608, 'STEP 3 - SITE OPS'!C75, 'STEP 3 - SITE OPS'!$I$2:$I$608) -> 0
A73: 2-29510.000 | B73: Material | C73: Vibration Monitoring | E73: 1 | F73: ls | H73: =SUMIF('STEP 3 - SITE OPS'!$C$2:$C$608, 'STEP 3 - SITE OPS'!C76, 'STEP 3 - SITE OPS'!$I$2:$I$608) -> 0
A74: 2-29515.000 | B74: Material | C74: Acoustic Testing | E74: 1 | F74: ls | H74: =SUMIF('STEP 3 - SITE OPS'!$C$2:$C$608, 'STEP 3 - SITE OPS'!C77, 'STEP 3 - SITE OPS'!$I$2:$I$608) -> 0
A75: 2-29520.000 | B75: Material | C75: Window Testing | E75: 1 | F75: ls | H75: =SUMIF('STEP 3 - SITE OPS'!$C$2:$C$608, 'STEP 3 - SITE OPS'!C78, 'STEP 3 - SITE OPS'!$I$2:$I$608) -> 0
A76: 2-29525.000 | B76: Material | C76: Weather Barrier Testing | E76: 1 | F76: ls | H76: =SUMIF('STEP 3 - SITE OPS'!$C$2:$C$608, 'STEP 3 - SITE OPS'!C79, 'STEP 3 - SITE OPS'!$I$2:$I$608) -> 0
A77: 2-29530.000 | B77: Material | C77: Gypcrete Testing | E77: 1 | F77: ls | H77: =SUMIF('STEP 3 - SITE OPS'!$C$2:$C$608, 'STEP 3 - SITE OPS'!C80, 'STEP 3 - SITE OPS'!$I$2:$I$608) -> 0
A78: 3-30000.000 | B78: Subcontract | C78: Concrete | E78: 1 | F78: ls | H78: =SUMIF('STEP 4 - ESTIMATE'!$C$2:$C$630, 'STEP 4 - ESTIMATE'!C29, 'STEP 4 - ESTIMATE'!$I$2:$I$630) -> 0
A79: 3-33543.000 | B79: Subcontract | C79: Polished Concrete | E79: 1 | F79: ls | H79: =SUMIF('STEP 4 - ESTIMATE'!C3:C630, 'STEP 4 - ESTIMATE'!C43, 'STEP 4 - ESTIMATE'!I3:I631) -> 0
A80: 3-34100.000 | B80: Subcontract | C80: Precast Structural Concrete | E80: 1 | F80: ls | H80: =SUMIF('STEP 4 - ESTIMATE'!C4:C630, 'STEP 4 - ESTIMATE'!C46, 'STEP 4 - ESTIMATE'!I4:I632) -> 0
A81: 3-34500.000 | B81: Subcontract | C81: Precast Architectural Concrete | E81: 1 | F81: ls | H81: =SUMIF('STEP 4 - ESTIMATE'!C5:C630, 'STEP 4 - ESTIMATE'!C47, 'STEP 4 - ESTIMATE'!I5:I633) -> 0
A82: 3-35413.000 | B82: Subcontract | C82: Gypcrete | E82: 1 | F82: ls | H82: =SUMIF('STEP 4 - ESTIMATE'!C6:C630, 'STEP 4 - ESTIMATE'!C50, 'STEP 4 - ESTIMATE'!I6:I634) -> 0
A83: 4-40000.000 | B83: Subcontract | C83: Masonry | E83: 1 | F83: ls | H83: =SUMIF('STEP 4 - ESTIMATE'!C7:C630, 'STEP 4 - ESTIMATE'!C55, 'STEP 4 - ESTIMATE'!I7:I635) -> 0
A84: 5-51200.000 | B84: Subcontract | C84: Structural Steel | E84: 1 | F84: ls | H84: =SUMIF('STEP 4 - ESTIMATE'!C8:C630, 'STEP 4 - ESTIMATE'!C65, 'STEP 4 - ESTIMATE'!I8:I636) -> 0
A85: 5-55000.000 | B85: Material | C85: Metal Fabrications | E85: 1 | F85: ls | H85: =SUMIF('STEP 4 - ESTIMATE'!C9:C630, 'STEP 4 - ESTIMATE'!C66, 'STEP 4 - ESTIMATE'!I9:I637) -> 0
A86: 5-57210.000 | B86: Subcontract | C86: Aluminum Deck and Railings | E86: 1 | F86: ls | H86: =SUMIF('STEP 4 - ESTIMATE'!C10:C630, 'STEP 4 - ESTIMATE'!C67, 'STEP 4 - ESTIMATE'!I10:I638) -> 0
A87: 6-61000.000 | B87: Material | C87: Rough Carpentry Material | E87: 1 | F87: ls | H87: =SUMIF('STEP 4 - ESTIMATE'!$C$2:$C$630, 'STEP 4 - ESTIMATE'!C76, 'STEP 4 - ESTIMATE'!$I$2:$I$630) -> 0
A88: 6-61010.000 | B88: Subcontract | C88: Rough Carpentry Installation | E88: 1 | F88: ls | H88: =SUMIF('STEP 4 - ESTIMATE'!$C$2:$C$630, 'STEP 4 - ESTIMATE'!C77, 'STEP 4 - ESTIMATE'!$I$2:$I$630) -> 0
A89: 6-61710.000 | B89: Material | C89: Manufactured Wall Panels | E89: 1 | F89: ls | H89: =SUMIF('STEP 4 - ESTIMATE'!$C$2:$C$630, 'STEP 4 - ESTIMATE'!C78, 'STEP 4 - ESTIMATE'!$I$2:$I$630) -> 0
A90: 6-61753.000 | B90: Material | C90: Wood Trusses | E90: 1 | F90: ls | H90: =SUMIF('STEP 4 - ESTIMATE'!$C$2:$C$630, 'STEP 4 - ESTIMATE'!C79, 'STEP 4 - ESTIMATE'!$I$2:$I$630) -> 0
A91: 6-61800.000 | B91: Material | C91: Glu-Laminated Construction | E91: 1 | F91: ls | H91: =SUMIF('STEP 4 - ESTIMATE'!$C$2:$C$630, 'STEP 4 - ESTIMATE'!C80, 'STEP 4 - ESTIMATE'!$I$2:$I$630) -> 0
A92: 6-62000.000 | B92: Subcontract | C92: Finish Carpentry Installation | E92: 1 | F92: ls | H92: =SUMIF('STEP 4 - ESTIMATE'!$C$2:$C$630, 'STEP 4 - ESTIMATE'!C82, 'STEP 4 - ESTIMATE'!$I$2:$I$630) -> 0
A93: 6-62200.000 | B93: Material | C93: Millwork | E93: 1 | F93: ls | H93: =SUMIF('STEP 4 - ESTIMATE'!$C$2:$C$630, 'STEP 4 - ESTIMATE'!C83, 'STEP 4 - ESTIMATE'!$I$2:$I$630) -> 0
A94: 6-64100.000 | B94: Subcontract | C94: Architectural Casework & Millwork | E94: 1 | F94: ls | H94: =SUMIF('STEP 4 - ESTIMATE'!$C$2:$C$630, 'STEP 4 - ESTIMATE'!C84, 'STEP 4 - ESTIMATE'!$I$2:$I$630) -> 0
A95: 6-66113.000 | B95: Subcontract | C95: Cultured Marble Fabrication | E95: 1 | F95: ls | H95: =SUMIF('STEP 4 - ESTIMATE'!$C$2:$C$630, 'STEP 4 - ESTIMATE'!C85, 'STEP 4 - ESTIMATE'!$I$2:$I$630) -> 0
A96: 6-66116.000 | B96: Subcontract | C96: Solid Surfacing and Ctops | E96: 1 | F96: ls | H96: =SUMIF('STEP 4 - ESTIMATE'!$C$2:$C$630, 'STEP 4 - ESTIMATE'!C86, 'STEP 4 - ESTIMATE'!$I$2:$I$630) -> 0
A97: 6-67300.000 | B97: Material | C97: Composite Decking | E97: 1 | F97: ls | H97: =SUMIF('STEP 4 - ESTIMATE'!$C$2:$C$630, 'STEP 4 - ESTIMATE'!C90, 'STEP 4 - ESTIMATE'!$I$2:$I$630) -> 0
A98: 6-68316.000 | B98: Material | C98: FRP Wall Paneling | E98: 1 | F98: ls | H98: =SUMIF('STEP 4 - ESTIMATE'!C26:C650, 'STEP 4 - ESTIMATE'!C87, 'STEP 4 - ESTIMATE'!I26:I650) -> 0
A99: 6-68700.000 | B99: Subcontract | C99: Pergolas | E99: 1 | F99: ls | H99: =SUMIF('STEP 4 - ESTIMATE'!C28:C651, 'STEP 4 - ESTIMATE'!C91, 'STEP 4 - ESTIMATE'!I28:I651) -> 0
A100: 7-71000.000 | B100: Subcontract | C100: Waterproofing | E100: 1 | F100: ls | H100: =SUMIF('STEP 4 - ESTIMATE'!$C$2:$C$630, 'STEP 4 - ESTIMATE'!C96, 'STEP 4 - ESTIMATE'!$I$2:$I$630) -> 0
A101: 7-71413.000 | B101: Subcontract | C101: Hot Fluid Applied Waterproofing | E101: 1 | F101: ls | H101: =SUMIF('STEP 4 - ESTIMATE'!$C$2:$C$630, 'STEP 4 - ESTIMATE'!C98, 'STEP 4 - ESTIMATE'!$I$2:$I$630) -> 0
...

Sheet Importer Data Fields
A1: Cost Code | B1: Cost Code Description | C1: Cost Type | D1: Cost Type Description | E1: BLI UOM | F1: BPQ UOM | G1: BOOLEAN
A2: 1-10000.000 | B2: General Conditions | C2: Equipment | D2: Equipment | E2: days | F2: ea | G2: True
A3: 1-10001.000 | B3: Preconstruction Fees | C3: Labor | D3: Labor | E3: hours | F3: ls | G3: False
A4: 1-10130.000 | B4: Design - Architecture | C4: Material | D4: Material | E4: months | F4: lf
A5: 1-10160.000 | B5: Design - Civil | C5: Other | D5: Other | E5: weeks | F5: m
A6: 1-10180.000 | B6: Design - MEP | C6: Subcontract | D6: Subcontract | E6: years | F6: mm
A7: 1-10210.000 | B7: Design - Structural | C7: User Def Type 6 | D7: User Def Type 6 | E7: ea | F7: m²
A8: 1-10230.000 | B8: Building Permit | C8: User Def Type 7 | D8: User Def Type 7 | E8: ls | F8: sf
A9: 1-10250.000 | B9: Demolition Permit | C9: User Def Type 8 | D9: User Def Type 8 | E9: lf | F9: sy
A10: 1-10260.000 | B10: City Licenses/Misc Permits | C10: User Def Type 9 | D10: User Def Type 9 | E10: m | F10: cy
A11: 1-10310.000 | B11: Project Executive | E11: mm | F11: m³
A12: 1-10320.000 | B12: Sr Project Manager | E12: m² | F12: kg
A13: 1-10330.000 | B13: Project Manager | E13: sf | F13: lbs
A14: 1-10340.000 | B14: Project Engineer | E14: sy | F14: t
A15: 1-10410.000 | B15: Sr Superintendent | E15: cy | F15: ton
A16: 1-10420.000 | B16: Superintendent | E16: m³
A17: 1-10430.000 | B17: Asst. Superintendent | E17: kg
A18: 1-10440.000 | B18: General Labor | E18: lbs
A19: 1-10510.000 | B19: Project Assistant | E19: t
A20: 1-10610.000 | B20: Safety Consultant, Visit Bi-Weekly | E20: ton
A21: 1-11000.000 | B21: Small Tools
A22: 1-11200.000 | B22: Fuel and Vehicle Charges
A23: 1-11400.000 | B23: Travel and Meals
A24: 1-11600.000 | B24: Procore
A25: 1-14010.000 | B25: Quality
A26: 1-15110.000 | B26: Temp Office and Set up
A27: 1-15111.000 | B27: Cell Phone
A28: 1-15112.000 | B28: Jobsite Office Equipment
A29: 1-15114.000 | B29: Project Computers / Internet
A30: 1-15120.000 | B30: Storage Trailer
A31: 1-15130.000 | B31: Dumpsters
A32: 1-15140.000 | B32: Temporary Toilets
... A225: 80-800001.000 | B225: Miscellaneous 1
